[1,["ecpdLyjvZBwrvm+cedCcQy","cd6wdS0S9DrJCadd3VBA8d","45VxNIBqJDH6is/tVOxYa9"],["node","_textureSetter","root","btnItem","imgRole","imgSelf","data","_spriteFrame"],[["cc.Node",["_name","_active","_components","_prefab","_contentSize","_parent","_children","_trs"],1,9,4,5,1,2,7],["cc.PrefabInfo",["fileId","root","asset"],2,1,1],["cc.Sprite",["node","_materials","_spriteFrame"],3,1,3,6],"cc.SpriteFrame",["cc.Prefab",["_name","asyncLoadAssets"],1],["365f9LglUtJ/oen3n7txs01",["node","imgSelf","imgRole","btnItem"],3,1,1,1,1],["cc.Widget",["_alignFlags","_top","node"],1,1],["cc.Button",["node"],3,1]],[[1,0,1,2,2],[4,0,1,3],[0,0,1,6,2,3,4,3],[0,0,5,6,2,3,4,7,2],[0,0,5,2,3,4,7,2],[0,0,5,2,3,4,2],[5,0,1,2,3,1],[1,1,2,1],[2,0,1,1],[2,0,1,2,1],[6,0,1,2,3],[7,0,1]],[[[{"name":"箭头","rect":[0,0,88,84],"offset":[0,0],"originalSize":[88,84],"capInsets":[0,0,0,0]}],[3],0,[0],[1],[1]],[[[1,"longgongRunItem",true],[2,"longgongRunItem",false,[-6,-7],[[6,-5,-4,-3,-2]],[7,-1,0],[5,150,150]],[3,"imgRole",1,[-9],[[8,-8,[2]]],[0,"78Eo2H6lZMUZEnU4AUd+uz",1,0],[5,119,111],[0,0,0,0,0,0,1,1.5,1.5,1]],[4,"imgSelf",2,[[9,-10,[0],1],[10,1,-73,-11]],[0,"04feDrigRDcLTx0Qq326SC",1,0],[5,88,84],[0,86.5,0,0,0,0,1,1,1,1]],[5,"btnItem",1,[[11,-12]],[0,"ceIc1SngFK/aqTsHMEHznk",1,0],[5,150,150]]],0,[0,2,1,0,3,4,0,4,2,0,5,3,0,0,1,0,-1,2,0,-2,4,0,0,2,0,-1,3,0,0,3,0,0,3,0,0,4,0,6,1,12],[0,0,0],[-1,7,-1],[0,2,0]]]]