[1,["ecpdLyjvZBwrvm+cedCcQy","06RGzRLpBCgZHPPYH1C1BQ","04D8QJISBFWKH2CB7eO97s","02Zf40dH1OXK3T6cZmhIYq","13PpZREX5OEIuCBLNnbCUm","90XfGorGBLMaTpP5wGPBPf","6dT7F85JlIdKYlgKKqvLJC","19Rl7QHJVDVI5Dgw9Uxrp0","29CLrgp/dHSLhEN7TSfveA","e5q0OXZChAP6zFQKJN7yTm","a5+w5Hu0NCZp9U0a6HXNhC"],["node","_spriteFrame","_parent","_textureSetter","root","data","itemBase"],[["cc.Node",["_name","_prefab","_contentSize","_components","_trs","_parent","_children","_color","_anchorPoint"],2,4,5,9,7,1,2,5,5],["cc.Sprite",["_sizeMode","_type","node","_materials","_spriteFrame"],1,1,3,6],["cc.PrefabInfo",["fileId","root","asset"],2,1,1],["cc.Button",["zoomScale","_N$transition","duration","node","clickEvents"],0,1,9],["cc.Label",["_string","_fontSize","_N$horizontalAlign","_N$verticalAlign","_lineHeight","node","_materials"],-2,1,3],"cc.SpriteFrame",["cc.Prefab",["_name"],2],["cc.Node",["_name","_parent","_children","_components","_prefab","_contentSize","_trs"],2,1,12,9,4,5,7],["cc.Widget",["_alignFlags","node"],2,1],["fea213VGE5IU6pfMdjca52X",["node","itemBase"],3,1,6],["cc.Layout",["_resize","_N$layoutType","_N$spacingX","_N$affectedByScale","node","_layoutSize"],-1,1,5],["cc.ClickEvent",["_componentId","handler"],1],["cc.LabelOutline",["_width","node","_color"],2,1,5],["cc.RichText",["_N$string","_N$fontSize","_N$lineHeight","node"],0,1]],[[2,0,1,2,2],[0,0,5,6,3,1,2,4,2],[1,1,0,2,3,4,3],[0,0,5,3,1,2,2],[1,2,3,4,1],[0,0,5,1,2,4,2],[0,0,5,3,1,2,4,2],[6,0,2],[0,0,6,3,1,2,4,2],[0,0,5,3,1,7,2,4,2],[0,0,5,3,1,7,2,8,4,2],[7,0,1,2,3,4,5,6,2],[8,0,1,2],[9,0,1,1],[2,1,2,1],[1,0,2,3,4,2],[10,0,1,2,3,4,5,5],[3,2,0,1,3,4],[3,0,1,3,4,3],[11,0,1,3],[4,0,1,2,3,5,6,5],[4,0,1,4,2,3,5,6,6],[12,0,1,2,2],[13,0,1,2,3,4]],[[[{"name":"重置","rect":[0,0,95,39],"offset":[0,0],"originalSize":[95,39],"capInsets":[0,0,0,0]}],[5],0,[0],[3],[1]],[[[7,"miFaResetView"],[8,"miFaResetView",[-4,-5],[[12,45,-2],[13,-3,18]],[14,-1,0],[5,750,1334],[375,667,0,0,0,0,1,1,1,1]],[11,"imgBg",1,[[-7,-8,-9,-10,[5,"itemNode1",-11,[0,"4a7Q81MIdK+qipgWMYujqE",1,0],[5,128,128],[-60,2.328,0,0,0,0,1,1,1,1]],[5,"itemNode2",-12,[0,"12ZwOiHp1D14SyWOBEyROT",1,0],[5,128,128],[60,0,0,0,0,0,1,1,1,1]]],1,1,1,1,4,4],[[2,1,0,-6,[16],17]],[0,"83QHd2oA5BsaydIEOzCKKo",1,0],[5,618,477],[-15,19,0,0,0,0,1,1,1,1]],[1,"imgTitle",2,[-14,-15],[[2,1,0,-13,[6],7]],[0,"3a6nhL9LFNfa4bu1WmcmQE",1,0],[5,300,60],[0,205.112,0,0,0,0,1,1,1,1]],[1,"gCost",2,[-17,-18],[[16,1,1,5,true,-16,[5,134.69,34]]],[0,"15SGQ1J1BOXZhruST7wXUu",1,0],[5,134.69,34],[0,-119.247,0,0,0,0,1,1,1,1]],[1,"btnCz",2,[-21],[[15,2,-19,[14],15],[17,0.05,0.92,3,-20]],[0,"b1BhZvA8ZN4pbkXs2iWFwI",1,0],[5,224,75],[0,-183.87,0,0,0,0,1,0.9,0.9,0]],[6,"btnClose",3,[[4,-22,[4],5],[18,0.9,3,-23,[[19,"33331LAYeFNT6aLgj3rPO3R","onClose"]]]],[0,"60DDpY7hFOgrpSdt2A9+e0",1,0],[5,53,50],[268,-2,0,0,0,0,1,1.4,1.4,0]],[1,"imgBottom",2,[-25],[[2,1,0,-24,[9],10]],[0,"98VcT/l4NJL6jhEy7Ggjvt",1,0],[5,600,170],[0,-0.9,0,0,0,0,1,1,1,1]],[3,"txtCancel",5,[[20,"重  置",32,1,1,-26,[13]],[22,2,-27,[4,4278190080]]],[0,"cdABAMhKJBx72ArsEV/CFT",1,0],[5,85.78,54.4]],[3,"imgMask",1,[[2,1,0,-28,[0],1]],[0,"23MtJ2RXBGwKYZJ3Nm/iWv",1,0],[5,750,1750]],[3,"txtTitle",3,[[4,-29,[2],3]],[0,"43zDrkxp1A0aJtxHxyb//a",1,0],[5,95,39]],[9,"txtContent",7,[[21,"重置将返回所有升级材料",26,26,1,1,-30,[8]]],[0,"18bUMqhxNCTZ+f2QDl2XBE",1,0],[4,4282532926],[5,286,32.76],[0,130.409,0,0,0,0,1,1,1,1]],[6,"imgCost",4,[[4,-31,[11],12]],[0,"6a5DGF/sFJxaDg7z32hUsq",1,0],[5,30,34],[-52.345,0,0,0,0,0,1,1,1,1]],[10,"txtCost",4,[[23,"<color=#00ff00>Rich</c>Text",26,24,-32]],[0,"3dFvKNnh5MOa0XBgqkvXL0",1,0],[4,4282532926],[5,99.69,30.240000000000002],[0,0,0.5],[-32.345,0,0,0,0,0,1,1,1,1]]],0,[0,4,1,0,0,1,0,0,1,0,-1,9,0,-2,2,0,0,2,0,-1,3,0,-2,7,0,-3,4,0,-4,5,0,2,2,0,2,2,0,0,3,0,-1,10,0,-2,6,0,0,4,0,-1,12,0,-2,13,0,0,5,0,0,5,0,-1,8,0,0,6,0,0,6,0,0,7,0,-1,11,0,0,8,0,0,8,0,0,9,0,0,10,0,0,11,0,0,12,0,0,13,0,5,1,32],[0,0,0,0,0,0,0,0,0,0,0,0,0,0,0,0,0,0,0],[-1,1,-1,1,-1,1,-1,1,-1,-1,1,-1,1,-1,-1,1,-1,1,6],[0,2,0,3,0,4,0,5,0,0,6,0,7,0,0,8,0,9,10]]]]