[1,["ceEvPhg69H+Y28/dmA5Qcn"],["_textureSetter"],["cc.SpriteFrame"],0,[[[{"name":"行走-skeleton-run_4","rect":[118,737,114,115],"offset":[-10,1],"originalSize":[136,121],"rotated":1,"capInsets":[0,0,0,0]}],[0],0,[0],[0],[0]],[[{"name":"行走-skeleton-run_10","rect":[2,620,110,107],"offset":[2,-3],"originalSize":[136,121],"rotated":1,"capInsets":[0,0,0,0]}],[0],0,[0],[0],[0]],[[{"name":"行走-skeleton-run_8","rect":[113,408,118,105],"offset":[3,-6],"originalSize":[136,121],"capInsets":[0,0,0,0]}],[0],0,[0],[0],[0]],[[{"name":"行走-skeleton-run_12","rect":[2,402,104,109],"offset":[0,-2],"originalSize":[136,121],"rotated":1,"capInsets":[0,0,0,0]}],[0],0,[0],[0],[0]],[[{"name":"行走-skeleton-run_0","rect":[111,515,116,107],"offset":[0,-7],"originalSize":[136,121],"capInsets":[0,0,0,0]}],[0],0,[0],[0],[0]],[[{"name":"行走-skeleton-run_14","rect":[2,508,110,107],"offset":[0,-5],"originalSize":[136,121],"rotated":1,"capInsets":[0,0,0,0]}],[0],0,[0],[0],[0]],[[{"name":"行走-skeleton-run_2","rect":[2,737,114,113],"offset":[-5,-1],"originalSize":[136,121],"capInsets":[0,0,0,0]}],[0],0,[0],[0],[0]],[[{"name":"行走-skeleton-run_6","rect":[111,624,116,111],"offset":[-4,-3],"originalSize":[136,121],"capInsets":[0,0,0,0]}],[0],0,[0],[0],[0]]]]