[1,["ecpdLyjvZBwrvm+cedCcQy","82hdB+nmRLlJ8GDY3fttQD","1fnptCdVJPXbFV+ckLj6j9","022MgJgJJLK7AR9D/30ADh","37p1KXyadP5rmDKit17Obq","7fxiVgwIhGKoe2eNmn78UZ","91br+tpqtK759bsrppRQny","24Ea5IRatMZaR+mfyS98Jy","a2MjXRFdtLlYQ5ouAFv/+R","b7xUDHjqNEbYAzxt4eLY+c","35vkvZNDtNurngMysb9A+8","fdKqOFrH5MZ4lRtxxEjHJL","c9y7foA0ZIgZJSyQabOKUs","02delMVqdBD70a/HSD99FK","55uvAhiRNPpoqQyB5W79AW"],["node","_textureSetter","_spriteFrame","root","buyTip","btnBuy","txtXianJia","txtYuanJia","giftLayer2","giftLayer1","txtTime","data","shortGiftPre","longGiftPre"],[["cc.Node",["_name","_components","_prefab","_contentSize","_parent","_trs","_children","_color","_anchorPoint"],2,9,4,5,1,7,2,5,5],"cc.SpriteFrame",["cc.PrefabInfo",["fileId","root","asset"],2,1,1],["cc.Sprite",["_sizeMode","node","_materials","_spriteFrame"],2,1,3,6],["cc.Label",["_fontSize","_lineHeight","_N$horizontalAlign","_N$verticalAlign","_string","node","_materials"],-2,1,3],["cc.Prefab",["_name"],2],["1a30e0B3hdCXplHqEGADxfu",["node","txtTime","giftLayer1","giftLayer2","txtYuanJia","txtXianJia","btnBuy","buyTip","shortGiftPre","longGiftPre"],3,1,1,1,1,1,1,1,1,6,6],["cc.Widget",["_alignFlags","_originalWidth","_originalHeight","node"],0,1],["cc.Button",["_N$transition","node"],2,1],["cc.LabelOutline",["_width","node","_color"],2,1,5],["cc.RichText",["_N$string","_N$fontSize","_N$lineHeight","node"],0,1],["cc.Layout",["_resize","_N$layoutType","_N$spacingX","node","_layoutSize"],0,1,5]],[[2,0,1,2,2],[3,1,2,3,1],[0,0,4,6,1,2,3,5,2],[4,4,0,1,2,3,5,6,6],[0,0,4,1,2,3,8,5,2],[0,0,4,1,2,3,2],[9,0,1,2,2],[0,0,4,1,2,7,3,8,5,2],[4,0,1,2,3,5,6,5],[11,0,1,2,3,4,4],[5,0,2],[0,0,6,1,2,3,5,2],[0,0,4,6,1,2,7,3,8,5,2],[0,0,4,1,2,3,5,2],[0,0,4,1,2,7,3,2],[6,0,1,2,3,4,5,6,7,8,9,1],[7,0,1,2,3,4],[2,1,2,1],[3,0,1,2,3,2],[8,0,1,2],[10,0,1,2,3,4]],[[[{"name":"红","rect":[0,0,625,46],"offset":[0,0],"originalSize":[625,46],"capInsets":[0,0,0,0]}],[1],0,[0],[1],[1]],[[{"name":"圆","rect":[0,0,86,86],"offset":[0,0],"originalSize":[86,86],"capInsets":[0,0,0,0]}],[1],0,[0],[1],[2]],[[{"name":"banner","rect":[0,0,630,270],"offset":[0,0],"originalSize":[630,270],"capInsets":[0,0,0,0]}],[1],0,[0],[1],[3]],[[{"name":"紫","rect":[0,0,625,46],"offset":[0,0],"originalSize":[625,46],"capInsets":[0,0,0,0]}],[1],0,[0],[1],[4]],[[[10,"hdChongZhiCuXiaoView"],[11,"hdChongZhiCuXiaoView",[-11,-12,-13,-14,-15,-16,-17,-18,-19,-20],[[15,-9,-8,-7,-6,-5,-4,-3,-2,18,19],[16,45,750,1334,-10]],[17,-1,0],[5,750,1334],[375,667,0,0,0,0,1,1,1,1]],[2,"btnBuy",1,[-23],[[1,-21,[13],14],[19,3,-22]],[0,"c0/e+uwdZKUJaBSCnTL6gw",1,0],[5,258,72],[95,-440,0,0,0,0,1,1,1,0]],[12,"txtYuanJia",1,[-25],[[8,30,30,1,1,-24,[10]]],[0,"1c9F7jLY5FlqeX04CkMIGA",1,0],[4,4278924109],[5,153.37,37.8],[0,0,0.5],[-248,-415,0,0,0,0,1,1,1,1]],[7,"txtXianJia",1,[[8,34,35,1,1,-26,[11]],[6,2,-27,[4,4278190080]]],[0,"c9CkMkKIRGe6TY/pd1XwGz",1,0],[4,4282436163],[5,4,48.1],[0,0,0.5],[-257,-455,0,0,0,0,1,1,1,1]],[2,"imgDescBg",1,[-29],[[1,-28,[16],17]],[0,"05qLqPnyNNhp+85WAPk1xT",1,0],[5,86,86],[233,-412,0,0,0,0,1,1,1,1]],[4,"txtTime",1,[[20,"",26,26,-30]],[0,"c0BdEk6R5OHL53Uy+a5dYr",1,0],[5,0,32.76],[0,0,0.5],[-303,280,0,0,0,0,1,1,1,1]],[2,"imgTitle1",1,[-32],[[1,-31,[3],4]],[0,"a3ascHzQRPLYSSUVtU3zrL",1,0],[5,625,46],[0,223,0,0,0,0,1,1,1,1]],[5,"txtTitle1",7,[[3,"超值礼包",28,30,1,1,-33,[2]],[6,2,-34,[4,4289871752]]],[0,"9c3Zf8PpVHqLokeuFJPmse",1,0],[5,116,41.8]],[4,"giftLayer1",1,[[9,1,1,5,-35,[5,625,195]]],[0,"2aJ1hNp0RG2p8CAL0HKpzB",1,0],[5,625,195],[0,0,0.5],[-314,100,0,0,0,0,1,1,1,1]],[2,"imgTitle2",1,[-37],[[1,-36,[6],7]],[0,"f1dpjXPRBPArXHwRCory1A",1,0],[5,625,46],[0,-28,0,0,0,0,1,1,1,1]],[5,"txtTitle2",10,[[3,"限购礼包",28,30,1,1,-38,[5]],[6,2,-39,[4,4280558777]]],[0,"85i8LbTrJLxb3Kym7SgYUO",1,0],[5,116,41.8]],[4,"giftLayer2",1,[[9,1,1,5,-40,[5,625,324]]],[0,"43u5BemnFPh5EC6pKoqRoB",1,0],[5,625,324],[0,0,0.5],[-314,-216,0,0,0,0,1,1,1,1]],[13,"ImgBanner",1,[[1,-41,[0],1]],[0,"a3uDLXzcJJFZPi0qMKjEf/",1,0],[5,630,270],[0,385,0,0,0,0,1,1,1,1]],[7,"imgLine",3,[[18,0,-42,[8],9]],[0,"04WfR06ChLXrzC7dkuPBxc",1,0],[4,4278924109],[5,150,2],[0,0,0.5],[0,-4.7,0,0,0,0,1,1,1,1]],[14,"txtBuy",2,[[3,"一键购买",32,32,1,1,-43,[12]]],[0,"9cJmT4bT1Pp5Wbj4nfug3D",1,0],[4,4279843816],[5,128,40.32]],[5,"txtDesc",5,[[3,"600%\n超值",20,20,1,1,-44,[15]]],[0,"82h2PzL3dNOItxmBkDaJpT",1,0],[5,51.15,45.2]]],0,[0,3,1,0,4,5,0,5,2,0,6,4,0,7,3,0,8,12,0,9,9,0,10,6,0,0,1,0,0,1,0,-1,13,0,-2,6,0,-3,7,0,-4,9,0,-5,10,0,-6,12,0,-7,3,0,-8,4,0,-9,2,0,-10,5,0,0,2,0,0,2,0,-1,15,0,0,3,0,-1,14,0,0,4,0,0,4,0,0,5,0,-1,16,0,0,6,0,0,7,0,-1,8,0,0,8,0,0,8,0,0,9,0,0,10,0,-1,11,0,0,11,0,0,11,0,0,12,0,0,13,0,0,14,0,0,15,0,0,16,0,11,1,44],[0,0,0,0,0,0,0,0,0,0,0,0,0,0,0,0,0,0,0,0],[-1,2,-1,-1,2,-1,-1,2,-1,2,-1,-1,-1,-1,2,-1,-1,2,12,13],[0,5,0,0,6,0,0,7,0,8,0,0,0,0,9,0,0,10,11,12]],[[{"name":"default_sprite_splash","rect":[0,0,2,2],"offset":[0,0],"originalSize":[2,2],"capInsets":[0,0,0,0]}],[1],0,[0],[1],[13]],[[{"name":"按钮","rect":[0,0,258,72],"offset":[0,0],"originalSize":[258,72],"capInsets":[0,0,0,0]}],[1],0,[0],[1],[14]]]]