[{"id":12011,"name":"飞镖1级","model":["百恋_技能_桃木飞剑"]},
{"id":12012,"name":"飞镖2级","model":["百恋_技能_桃木飞剑"]},
{"id":12013,"name":"飞镖3级","model":["百恋_技能_桃木飞剑"]},
{"id":12014,"name":"飞镖4级","model":["百恋_技能_桃木飞剑"]},
{"id":12015,"name":"飞镖5级","model":["百恋_技能_桃木飞剑"]},
{"id":12016,"name":"飞镖_突破","model":["百恋_技能_逍遥飞剑"]},
{"id":12021,"name":"弩箭1级","model":["百恋_技能_千机弩"]},
{"id":12022,"name":"弩箭2级","model":["百恋_技能_千机弩"]},
{"id":12023,"name":"弩箭3级","model":["百恋_技能_千机弩"]},
{"id":12024,"name":"弩箭4级","model":["百恋_技能_千机弩"]},
{"id":12025,"name":"弩箭5级","model":["百恋_技能_千机弩"]},
{"id":12026,"name":"弩箭_突破","model":["百恋_技能_孔雀翎"]},
{"id":12031,"name":"太刀_白1级","model":["百恋_技能_修罗刀"]},
{"id":12032,"name":"太刀_白2级","model":["百恋_技能_修罗刀"]},
{"id":12033,"name":"太刀_白3级","model":["百恋_技能_修罗刀"]},
{"id":12034,"name":"太刀_白4级","model":["百恋_技能_修罗刀"]},
{"id":12035,"name":"太刀_白5级","model":["百恋_技能_修罗刀"]},
{"id":12036,"name":"太刀_白_突破","model":["百恋_技能_噬魂修罗"]},
{"id":12037,"name":"太刀_剑气1级","model":["百恋_技能_太刀刀光"]},
{"id":12038,"name":"太刀_剑气2级","model":["百恋_技能_太刀刀光"]},
{"id":12039,"name":"太刀_剑气3级","model":["百恋_技能_太刀刀光"]},
{"id":12040,"name":"太刀_剑气4级","model":["百恋_技能_太刀刀光"]},
{"id":12041,"name":"太刀_剑气5级","model":["百恋_技能_太刀刀光"]},
{"id":12042,"name":"太刀_剑气_突破","model":["百恋_技能_太刀刀光"]},
{"id":12051,"name":"S太刀_普攻1级","model":["百恋_技能_弑神八荒"]},
{"id":12052,"name":"S太刀_普攻2级","model":["百恋_技能_弑神八荒"]},
{"id":12053,"name":"S太刀_普攻3级","model":["百恋_技能_弑神八荒"]},
{"id":12054,"name":"S太刀_普攻4级","model":["百恋_技能_弑神八荒"]},
{"id":12055,"name":"S太刀_普攻5级","model":["百恋_技能_弑神八荒"]},
{"id":12056,"name":"S太刀_回旋斩1级","model":["百恋_装备技能_万魂波动"]},
{"id":12057,"name":"S太刀_回旋斩2级","model":["百恋_装备技能_万魂波动"]},
{"id":12058,"name":"S太刀_回旋斩3级","model":["百恋_装备技能_万魂波动"]},
{"id":12059,"name":"S太刀_回旋斩4级","model":["百恋_装备技能_万魂波动"]},
{"id":12060,"name":"S太刀_回旋斩5级","model":["百恋_装备技能_万魂波动"]},
{"id":12061,"name":"S太刀_突破","model":["百恋_技能_弑神八荒觉醒"]},
{"id":12062,"name":"S太刀_突破","model":["百恋_技能_弑神八荒觉醒"]},
{"id":12063,"name":"S太刀_突破_回旋斩","model":["百恋_装备技能_万魂波动"]},
{"id":12064,"name":"S太刀_红_剑阵1级","model":["百恋_装备技能_修炼领域"]},
{"id":12065,"name":"S太刀_红_剑阵2级","model":["百恋_装备技能_修炼领域"]},
{"id":12066,"name":"S太刀_红_剑阵3级","model":["百恋_装备技能_修炼领域"]},
{"id":12067,"name":"S太刀_红_剑阵4级","model":["百恋_装备技能_修炼领域"]},
{"id":12068,"name":"S太刀_红_剑阵5级","model":["百恋_装备技能_修炼领域"]},
{"id":12071,"name":"弓箭1级","model":["百恋_技能_黑曲弓"]},
{"id":12072,"name":"弓箭2级","model":["百恋_技能_黑曲弓"]},
{"id":12073,"name":"弓箭3级","model":["百恋_技能_黑曲弓"]},
{"id":12074,"name":"弓箭4级","model":["百恋_技能_黑曲弓"]},
{"id":12075,"name":"弓箭5级","model":["百恋_技能_黑曲弓"]},
{"id":12076,"name":"弓箭6级","model":["百恋_技能_黑曲弓觉醒"]},
{"id":12081,"name":"燕返术1级","model":["百恋_技能_燕返术"]},
{"id":12082,"name":"燕返术2级","model":["百恋_技能_燕返术"]},
{"id":12083,"name":"燕返术3级","model":["百恋_技能_燕返术"]},
{"id":12084,"name":"燕返术4级","model":["百恋_技能_燕返术"]},
{"id":12085,"name":"燕返术5级","model":["百恋_技能_燕返术"]},
{"id":12086,"name":"百鸟归巢","model":["百恋_技能_百鸟归巢"]},
{"id":12091,"name":"灵蛇咒1级","model":["百恋_技能_灵蛇咒_毒瓶","百恋_技能_灵蛇咒_毒液"]},
{"id":12092,"name":"灵蛇咒2级","model":["百恋_技能_灵蛇咒_毒瓶","百恋_技能_灵蛇咒_毒液"]},
{"id":12093,"name":"灵蛇咒3级","model":["百恋_技能_灵蛇咒_毒瓶","百恋_技能_灵蛇咒_毒液"]},
{"id":12094,"name":"灵蛇咒4级","model":["百恋_技能_灵蛇咒_毒瓶","百恋_技能_灵蛇咒_毒液"]},
{"id":12095,"name":"灵蛇咒5级","model":["百恋_技能_灵蛇咒_毒瓶","百恋_技能_灵蛇咒_毒液"]},
{"id":12096,"name":"冥蛇咒","model":["百恋_技能_冥蛇咒_毒瓶","百恋_技能_冥蛇咒_毒液"]},
{"id":12101,"name":"护体金光1级","model":["百恋_技能_护体金光"]},
{"id":12102,"name":"护体金光2级","model":["百恋_技能_护体金光"]},
{"id":12103,"name":"护体金光3级","model":["百恋_技能_护体金光"]},
{"id":12104,"name":"护体金光4级","model":["百恋_技能_护体金光"]},
{"id":12105,"name":"护体金光5级","model":["百恋_技能_护体金光"]},
{"id":12106,"name":"佛怒金莲","model":["百恋_技能_佛怒莲华"]},
{"id":12111,"name":"佛像1级","model":["百恋_技能_地藏像"]},
{"id":12112,"name":"佛像2级","model":["百恋_技能_地藏像"]},
{"id":12113,"name":"佛像3级","model":["百恋_技能_地藏像"]},
{"id":12114,"name":"佛像4级","model":["百恋_技能_地藏像"]},
{"id":12115,"name":"佛像5级","model":["百恋_技能_地藏像"]},
{"id":12116,"name":"降魔杵","model":["百恋_技能_降魔杵"]},
{"id":12121,"name":"火灵咒1级","model":["百恋_技能_火灵咒_飞行","百恋_技能_火灵咒_命中"]},
{"id":12122,"name":"火灵咒2级","model":["百恋_技能_火灵咒_飞行","百恋_技能_火灵咒_命中"]},
{"id":12123,"name":"火灵咒3级","model":["百恋_技能_火灵咒_飞行","百恋_技能_火灵咒_命中"]},
{"id":12124,"name":"火灵咒4级","model":["百恋_技能_火灵咒_飞行","百恋_技能_火灵咒_命中"]},
{"id":12125,"name":"火灵咒5级","model":["百恋_技能_火灵咒_飞行","百恋_技能_火灵咒_命中"]},
{"id":12126,"name":"炎雀焚天","model":["百恋_技能_炎雀焚天_飞行","百恋_技能_炎雀焚天_命中"]},
{"id":12131,"name":"天剑_无邪1级","model":["百恋_技能_无邪剑_攻击","百恋_技能_无邪剑瞄准","百恋_技能_无邪剑受击"]},
{"id":12132,"name":"天剑_无邪2级","model":["百恋_技能_无邪剑_攻击","百恋_技能_无邪剑瞄准","百恋_技能_无邪剑受击"]},
{"id":12133,"name":"天剑_无邪3级","model":["百恋_技能_无邪剑_攻击","百恋_技能_无邪剑瞄准","百恋_技能_无邪剑受击"]},
{"id":12134,"name":"天剑_无邪4级","model":["百恋_技能_无邪剑_攻击","百恋_技能_无邪剑瞄准","百恋_技能_无邪剑受击"]},
{"id":12135,"name":"天剑_无邪5级","model":["百恋_技能_无邪剑_攻击","百恋_技能_无邪剑瞄准","百恋_技能_无邪剑受击"]},
{"id":12136,"name":"天剑_无邪6级","model":["百恋_技能_神剑诛仙_攻击","百恋_技能_神剑瞄准","百恋_技能_神剑受击"]},
{"id":12137,"name":"魔剑_断魂1级","model":["百恋_技能_断魂剑_攻击","百恋_技能_断魂剑瞄准","百恋_技能_断魂剑受击"]},
{"id":12138,"name":"魔剑_断魂2级","model":["百恋_技能_断魂剑_攻击","百恋_技能_断魂剑瞄准","百恋_技能_断魂剑受击"]},
{"id":12139,"name":"魔剑_断魂3级","model":["百恋_技能_断魂剑_攻击","百恋_技能_断魂剑瞄准","百恋_技能_断魂剑受击"]},
{"id":12140,"name":"魔剑_断魂4级","model":["百恋_技能_断魂剑_攻击","百恋_技能_断魂剑瞄准","百恋_技能_断魂剑受击"]},
{"id":12141,"name":"魔剑_断魂5级","model":["百恋_技能_断魂剑_攻击","百恋_技能_断魂剑瞄准","百恋_技能_断魂剑受击"]},
{"id":12142,"name":"魔剑_断魂6级","model":["百恋_技能_神剑诛仙_攻击","百恋_技能_神剑瞄准","百恋_技能_神剑受击"]},
{"id":12151,"name":"游龙术1级","model":["百恋_技能_游龙术"]},
{"id":12152,"name":"游龙术2级","model":["百恋_技能_游龙术"]},
{"id":12153,"name":"游龙术3级","model":["百恋_技能_游龙术"]},
{"id":12154,"name":"游龙术4级","model":["百恋_技能_游龙术"]},
{"id":12155,"name":"游龙术5级","model":["百恋_技能_游龙术"]},
{"id":12156,"name":"龙腾伏魔咒","model":["百恋_技能_龙神伏魔咒"]},
{"id":12161,"name":"阴阳盘1级","model":["百恋_技能_阴阳盘"]},
{"id":12162,"name":"阴阳盘2级","model":["百恋_技能_阴阳盘"]},
{"id":12163,"name":"阴阳盘3级","model":["百恋_技能_阴阳盘"]},
{"id":12164,"name":"阴阳盘4级","model":["百恋_技能_阴阳盘"]},
{"id":12165,"name":"阴阳盘5级","model":["百恋_技能_阴阳盘"]},
{"id":12166,"name":"驱魔法盘","model":["百恋_技能_驱魔法盘"]},
{"id":12171,"name":"幽冥火1级","model":["百恋_技能_破煞刀"]},
{"id":12172,"name":"幽冥火2级","model":["百恋_技能_破煞刀"]},
{"id":12173,"name":"幽冥火3级","model":["百恋_技能_破煞刀"]},
{"id":12174,"name":"幽冥火4级","model":["百恋_技能_破煞刀"]},
{"id":12175,"name":"幽冥火5级","model":["百恋_技能_破煞刀"]},
{"id":12176,"name":"附身神符","model":["百恋_技能_诛天斩魂"]},
{"id":12181,"name":"天雷咒1级","model":["百恋_技能_天雷咒"]},
{"id":12182,"name":"天雷咒2级","model":["百恋_技能_天雷咒"]},
{"id":12183,"name":"天雷咒3级","model":["百恋_技能_天雷咒"]},
{"id":12184,"name":"天雷咒4级","model":["百恋_技能_天雷咒"]},
{"id":12185,"name":"天雷咒5级","model":["百恋_技能_天雷咒"]},
{"id":12186,"name":"天罚惊雷","model":["百恋_技能_天罚惊雷"]},
{"id":12191,"name":"雪童子1级","model":["百恋_技能_雪童子"]},
{"id":12192,"name":"雪童子2级","model":["百恋_技能_雪童子"]},
{"id":12193,"name":"雪童子3级","model":["百恋_技能_雪童子"]},
{"id":12194,"name":"雪童子4级","model":["百恋_技能_雪童子"]},
{"id":12195,"name":"雪童子5级","model":["百恋_技能_雪童子"]},
{"id":12196,"name":"冰凌雪女","model":["百恋_技能_冰凌雪女"]},
{"id":12197,"name":"冰刺","model":["百恋_技能_冰凌雪女_冰碎"]},
{"id":12201,"name":"永恒战靴_火焰路径","model":[]},
{"id":12202,"name":"永恒战靴_火焰路径_增强","model":[]},
{"id":12203,"name":"减速_紫犬牙项链","model":[]},
{"id":12204,"name":"减速_橙犬牙项链","model":[]},
{"id":12205,"name":"风暴_橙虫壳外衣","model":[]},
{"id":12206,"name":"辐射脉冲_紫厚重防护服","model":[]},
{"id":12207,"name":"辐射脉冲_橙厚重防护服","model":[]},
{"id":12208,"name":"辐射圈_紫原石项链","model":[]},
{"id":12209,"name":"辐射圈_橙原石项链","model":[]},
{"id":12210,"name":"辐射脉冲_紫厚重腰带","model":[]},
{"id":12211,"name":"辐射脉冲_橙厚重腰带","model":[]},
{"id":12212,"name":"辐射圈_紫厚重手套","model":[]},
{"id":12213,"name":"辐射圈_橙厚重手套","model":[]},
{"id":12214,"name":"辐射圈_紫厚重战靴","model":[]},
{"id":12221,"name":"玄刀阵1级","model":["百恋_技能_玄刀阵"]},
{"id":12222,"name":"玄刀阵2级","model":["百恋_技能_玄刀阵"]},
{"id":12223,"name":"玄刀阵3级","model":["百恋_技能_玄刀阵"]},
{"id":12224,"name":"玄刀阵4级","model":["百恋_技能_玄刀阵"]},
{"id":12225,"name":"玄刀阵5级","model":["百恋_技能_玄刀阵"]},
{"id":12226,"name":"皎月罗刹","model":["百恋_技能_皎月罗刹"]},
{"id":12231,"name":"棒球棍1级","model":["百恋_技能_伏魔杖"]},
{"id":12232,"name":"棒球棍2级","model":["百恋_技能_伏魔杖"]},
{"id":12233,"name":"棒球棍3级","model":["百恋_技能_伏魔杖"]},
{"id":12234,"name":"棒球棍4级","model":["百恋_技能_伏魔杖"]},
{"id":12235,"name":"棒球棍5级","model":["百恋_技能_伏魔杖"]},
{"id":12236,"name":"觉醒棒球棍","model":["百恋_技能_驱魔法棍"]},
{"id":12241,"name":"轮回法球1","model":["百恋_技能_轮回法球"]},
{"id":12242,"name":"轮回法球2","model":["百恋_技能_轮回法球"]},
{"id":12243,"name":"轮回法球3","model":["百恋_技能_轮回法球"]},
{"id":12244,"name":"轮回法球4","model":["百恋_技能_轮回法球"]},
{"id":12245,"name":"轮回法球5","model":["百恋_技能_轮回法球"]},
{"id":12246,"name":"觉醒轮回法球","model":["百恋_技能_六道轮回"]},
{"id":12251,"name":"棒球棍1级","model":["百恋_技能_伏魔杖"]},
{"id":12252,"name":"棒球棍2级","model":["百恋_技能_伏魔杖"]},
{"id":12253,"name":"棒球棍3级","model":["百恋_技能_伏魔杖"]},
{"id":12254,"name":"棒球棍4级","model":["百恋_技能_伏魔杖"]},
{"id":12255,"name":"棒球棍5级","model":["百恋_技能_伏魔杖"]},
{"id":12261,"name":"爆破箭1级","model":["百恋_技能_黑曲弓","百恋_技能_火灵咒_命中"]},
{"id":12262,"name":"爆破箭2级","model":["百恋_技能_黑曲弓","百恋_技能_火灵咒_命中"]},
{"id":12263,"name":"爆破箭3级","model":["百恋_技能_黑曲弓","百恋_技能_火灵咒_命中"]},
{"id":12264,"name":"爆破箭4级","model":["百恋_技能_黑曲弓","百恋_技能_火灵咒_命中"]},
{"id":12265,"name":"爆破箭5级","model":["百恋_技能_黑曲弓","百恋_技能_火灵咒_命中"]},
{"id":12266,"name":"爆破箭6级","model":["百恋_技能_黑曲弓觉醒","百恋_技能_火灵咒_命中"]},
{"id":12401,"name":"铜尸射手","model":["百恋_怪物子弹_铜尸射手"]},
{"id":12402,"name":"勾魂使","model":["百恋_怪物子弹_勾魂使"]},
{"id":12403,"name":"地藏王_低级","model":["百恋_怪物子弹_地藏王_低级"]},
{"id":12404,"name":"地藏王_高级","model":["百恋_怪物子弹_地藏王_高级"]},
{"id":12405,"name":"妖道僵尸","model":["百恋_怪物子弹_妖道僵尸"]},
{"id":12406,"name":"山精","model":["百恋_怪物子弹_山精"]},
{"id":12407,"name":"山魁","model":["百恋_怪物子弹_山魁"]},
{"id":12408,"name":"巨斧战尸","model":["百恋_怪物子弹_巨斧战尸"]},
{"id":12409,"name":"拉面鬼","model":["百恋_怪物子弹_拉面鬼"]},
{"id":12410,"name":"独眼鬼","model":["百恋_怪物子弹_独眼鬼"]},
{"id":12411,"name":"玉灵花妖","model":["百恋_怪物子弹_玉灵花妖"]},
{"id":12412,"name":"疯婆僵尸","model":["百恋_怪物子弹_疯婆僵尸"]},
{"id":12413,"name":"白无常","model":["百恋_怪物子弹_白无常"]},
{"id":12414,"name":"白龙","model":["百恋_怪物子弹_白龙"]},
{"id":12415,"name":"矿坑小鬼","model":["百恋_怪物子弹_矿坑小鬼"]},
{"id":12416,"name":"粉蛾","model":["百恋_怪物子弹_粉蛾"]},
{"id":12417,"name":"紫灵花妖","model":["百恋_怪物子弹_紫灵花妖"]},
{"id":12418,"name":"紫色泡泡蛙","model":["百恋_怪物子弹_紫色泡泡蛙"]},
{"id":12419,"name":"花莹","model":["百恋_怪物子弹_花莹"]},
{"id":12420,"name":"蛇妇妖","model":["百恋_怪物子弹_蛇妇妖"]},
{"id":12421,"name":"蛇妖姬","model":["百恋_怪物子弹_蛇妖姬"]},
{"id":12422,"name":"酒鬼","model":["百恋_怪物子弹_酒鬼"]},
{"id":12423,"name":"野鸡精","model":["百恋_怪物子弹_野鸡精"]},
{"id":12424,"name":"铜尸射手","model":["百恋_怪物子弹_铜尸射手"]},
{"id":12425,"name":"长枪战尸","model":["百恋_怪物子弹_长枪战尸"]},
{"id":12426,"name":"雷子","model":["百恋_怪物子弹_雷子"]},
{"id":12427,"name":"青坊主","model":["百恋_怪物子弹_青坊主"]},
{"id":12428,"name":"青灯小鬼","model":["百恋_怪物子弹_青灯小鬼"]},
{"id":12429,"name":"鬼巫射手","model":["百恋_怪物子弹_鬼巫射手"]},
{"id":12430,"name":"鬼灵使者","model":["百恋_怪物子弹_鬼灵使者"]},
{"id":12431,"name":"黄色泡泡蛙","model":["百恋_怪物子弹_黄色泡泡蛙"]},
{"id":12432,"name":"(测试没用可删)毒液亡语","model":["百恋_技能_灵蛇咒_毒液"]},
{"id":12433,"name":"三叶妖种子弹","model":["百恋_怪物子弹_三叶妖"]},
{"id":12434,"name":"肥僵尸附身，符","model":["百恋_怪物子弹_肥僵尸"]},
{"id":12435,"name":"玉灵花妖散花弹","model":["百恋_怪物子弹_玉灵花妖"]},
{"id":12436,"name":"战俘僵尸铁球旋转，符","model":["百恋_怪物子弹_战俘僵尸"]},
{"id":12437,"name":"龙萤毒刺","model":["百恋_怪物子弹_龙萤"]},
{"id":12438,"name":"尸香魔芋，毒藤陷阱","model":["百恋_亡语_毒藤"]},
{"id":12439,"name":"毒液蜘蛛亡语","model":["百恋_亡语_绿"]},
{"id":12440,"name":"巨盾战尸，旋转护盾，符","model":["百恋_怪物子弹_巨盾战尸"]},
{"id":12441,"name":"盗棺亡者，4道飞符","model":["百恋_怪物子弹_盗棺亡者"]},
{"id":12442,"name":"火灵，火焰飞弹3发","model":["百恋_怪物子弹_火灵"]},
{"id":12443,"name":"封魔老妖，开花眼球弹","model":["百恋_怪物子弹_封魔老妖"]},
{"id":12444,"name":"红衣新娘，旋转匕首，符","model":["百恋_怪物子弹_红衣新娘"]},
{"id":12445,"name":"闹尸棺，扇形骷髅子弹","model":["百恋_怪物子弹_闹尸棺"]},
{"id":12446,"name":"马面，战斧投掷","model":["百恋_怪物子弹_马面"]},
{"id":12447,"name":"白无常，万花弹","model":["百恋_怪物子弹_白无常"]},
{"id":12448,"name":"血蜘蛛亡语","model":["百恋_亡语_红"]},
{"id":12449,"name":"入夜魔，三方向魔爪","model":["百恋_怪物子弹_入夜魔"]},
{"id":12450,"name":"狂暴狼王，利爪撕咬","model":["百恋_怪物子弹_狂暴狼王"]},
{"id":12451,"name":"血爆骷髅，巨大木桶","model":["百恋_怪物子弹_血爆骷髅"]},
{"id":12452,"name":"黑无常，八方黑咒","model":["百恋_怪物子弹_黑无常"]},
{"id":12453,"name":"百炼狼王，5方向散散射击","model":["百恋_怪物子弹_通用子弹红"]},
{"id":12454,"name":"鬼魅黑蜘蛛，獠牙弹","model":["百恋_怪物子弹_鬼魅蜘蛛"]},
{"id":12455,"name":"僵尸王，8方向血珠围绕，符","model":["百恋_怪物子弹_僵尸王"]},
{"id":12456,"name":"胖鬼，旋转酒瓶，符","model":["百恋_怪物子弹_胖鬼"]},
{"id":12457,"name":"拉面鬼，玉子飞饼3发，符","model":["百恋_怪物子弹_拉面鬼"]},
{"id":12458,"name":"蛇妇妖，三发子弹","model":["百恋_怪物子弹_蛇妇妖"]},
{"id":12459,"name":"欲念鬼，呕吐物，边走边拉","model":["百恋_怪物子弹_欲念鬼团"]},
{"id":12460,"name":"蛇妖姬，6方向蛇子弹","model":["百恋_怪物子弹_蛇妖姬"]},
{"id":12461,"name":"相扑妖怪，轮旋滚轮3个方向，自己","model":["百恋_怪物子弹_鬼相扑妖"]},
{"id":12462,"name":"青坊主三发冰晶","model":["百恋_怪物子弹_青坊主"]},
{"id":12463,"name":"酒吞童子螺旋酒馆8个方向子弹，螺旋","model":["百恋_怪物子弹_酒吞童子"]},
{"id":12464,"name":"紫色灵花妖，撒花弹，","model":["百恋_怪物子弹_尸香魔芋"]},
{"id":12465,"name":"红山魁旋转狼牙棒，","model":["百恋_怪物子弹_山魁"]},
{"id":12466,"name":"巨石魔，旋转石头护盾，符","model":["百恋_怪物子弹_巨石魔"]},
{"id":12467,"name":"灵芝王，蘑菇子弹，六发","model":["百恋_怪物子弹_灵芝王"]},
{"id":12468,"name":"玉灵花妖，三发子弹","model":["百恋_怪物子弹_玉灵花妖"]},
{"id":12469,"name":"毒藤妖王，8个方向藤蔓冲击","model":["百恋_怪物子弹_毒藤妖王"]},
{"id":12470,"name":"粉蛾散弹，三发","model":["百恋_怪物子弹_粉蛾"]},
{"id":12471,"name":"剧毒蛾，撒花弹","model":["百恋_怪物子弹_尸香魔芋"]},
{"id":12472,"name":"鸡贼老鼠，旋转棍棒，高频率释放","model":["百恋_怪物子弹_鸡贼鼠"]},
{"id":12473,"name":"画魂，撒花弹飞鸟","model":["百恋_怪物子弹_画魂"]},
{"id":12474,"name":"疯婆僵尸三方向旋转菜刀，频繁释放","model":["百恋_怪物子弹_疯婆僵尸"]},
{"id":12475,"name":"符咒魔，高频率三方向子弹","model":["百恋_怪物子弹_符咒魔"]},
{"id":12476,"name":"铁甲僵尸，旋转护盾，符","model":["百恋_怪物子弹_铁甲尸"]},
{"id":12477,"name":"旋风刀客，旋转飞镖，撒花弹","model":["百恋_怪物子弹_旋风刀客"]},
{"id":12478,"name":"紫色灵花妖，撒花弹，","model":["百恋_怪物子弹_尸香魔芋"]},
{"id":12479,"name":"彼岸花妖，缓慢子弹，8方向","model":["百恋_怪物子弹_彼岸花妖"]},
{"id":12480,"name":"妖道僵尸，三道飞符","model":["百恋_怪物子弹_妖道僵尸"]},
{"id":12481,"name":"千年树妖，鬼火围绕，符","model":["百恋_怪物子弹_千年树妖"]},
{"id":12482,"name":"幻灵女鬼，散射","model":["百恋_怪物子弹_幻灵女鬼"]},
{"id":12483,"name":"黑山老妖，8方向飞石头","model":["百恋_怪物子弹_黑山老妖"]},
{"id":12484,"name":"鬼婆子弹","model":["百恋_怪物子弹_鬼婆"]},
{"id":12485,"name":"傀儡女鬼飞弹","model":["百恋_怪物子弹_傀儡女鬼"]},
{"id":12486,"name":"蝙蝠子弹千年蝠妖","model":["百恋_怪物子弹_千年蝠王"]},
{"id":12487,"name":"尸鳖虫子弹","model":["百恋_怪物子弹_尸鳖虫王"]},
{"id":12488,"name":"寄尸蟹子弹飞弹","model":["百恋_怪物子弹_寄尸蟹"]},
{"id":12489,"name":"晶石蜘蛛护盾，符","model":["百恋_怪物子弹_晶石蜘蛛"]},
{"id":12490,"name":"僵尸将军，大刀光弹幕","model":["百恋_怪物子弹_僵尸将军"]},
{"id":12491,"name":"夜罗刹，追魂手","model":["百恋_怪物子弹_夜罗刹"]},
{"id":12492,"name":"鬼灵武士飞符","model":["百恋_怪物子弹_鬼灵武士"]},
{"id":12493,"name":"百变猴王，大闹天空","model":["百恋_怪物子弹_百变猴王"]},
{"id":12494,"name":"爆炸火灵","model":["百恋_怪物子弹_爆炸火灵"]},
{"id":12495,"name":"欲念鬼，呕吐物，边走边拉","model":["百恋_怪物子弹_欲念鬼团"]},
{"id":12496,"name":"自爆","model":["百恋_怪物子弹_爆炸火灵"]},
{"id":12497,"name":"白无常，万花弹","model":["百恋_怪物子弹_白无常"]},
{"id":12501,"name":"百恋_装备技能_一次护盾","model":["百恋_装备技能_一次护盾"]},
{"id":12511,"name":"百恋_装备技能_万魂波动","model":["百恋_装备技能_万魂波动"]},
{"id":12503,"name":"百恋_装备技能_伤害减免","model":["百恋_装备技能_伤害减免"]},
{"id":12504,"name":"百恋_装备技能_伤害提升","model":["百恋_装备技能_伤害提升"]},
{"id":12505,"name":"百恋_装备技能_修炼领域","model":["百恋_装备技能_修炼领域"]},
{"id":12506,"name":"百恋_装备技能_加速","model":["百恋_装备技能_加速"]},
{"id":12507,"name":"百恋_装备技能_太刀刀光","model":["百恋_装备技能_太刀刀光"]},
{"id":12508,"name":"百恋_装备技能_小范围爆炸","model":["百恋_装备技能_小范围爆炸"]},
{"id":12509,"name":"百恋_装备技能_弓箭爆炸","model":["百恋_装备技能_弓箭爆炸"]},
{"id":12510,"name":"百恋_装备技能_强力脉冲","model":["百恋_装备技能_强力脉冲"]},
{"id":12511,"name":"百恋_装备技能_战场统治者","model":["百恋_装备技能_战场统治者"]},
{"id":12512,"name":"百恋_装备技能_护盾冲击波","model":["百恋_装备技能_护盾冲击波"]},
{"id":12513,"name":"百恋_装备技能_护盾冲击波_推开","model":["百恋_装备技能_护盾冲击波_推开"]},
{"id":12514,"name":"百恋_装备技能_无敌","model":["百恋_装备技能_无敌"]},
{"id":12515,"name":"百恋_装备技能_流血","model":["百恋_装备技能_流血"]},
{"id":12516,"name":"百恋_装备技能_激励","model":["百恋_装备技能_激励"]},
{"id":12517,"name":"百恋_装备技能_秒杀","model":["百恋_装备技能_秒杀"]},
{"id":12518,"name":"百恋_装备技能_范围减速","model":["百恋_装备技能_范围减速"]},
{"id":12519,"name":"百恋_装备技能_辐射圈","model":["百恋_装备技能_辐射圈"]},
{"id":12520,"name":"百恋_装备技能_辐射圈2","model":["百恋_装备技能_辐射圈2"]},
{"id":12521,"name":"百恋_装备技能_重击","model":["百恋_装备技能_重击"]},
{"id":12601,"name":"飞镖1级","model":["百恋_技能_桃木飞剑"]},
{"id":12602,"name":"飞镖2级","model":["百恋_技能_桃木飞剑"]},
{"id":12603,"name":"飞镖3级","model":["百恋_技能_桃木飞剑"]},
{"id":12604,"name":"飞镖4级","model":["百恋_技能_桃木飞剑"]},
{"id":12605,"name":"飞镖5级","model":["百恋_技能_桃木飞剑"]},
{"id":12606,"name":"飞镖_突破","model":["百恋_技能_逍遥飞剑"]},
{"id":12611,"name":"弩箭_紫1级","model":["百恋_技能_千机弩"]},
{"id":12612,"name":"弩箭_紫2级","model":["百恋_技能_千机弩"]},
{"id":12613,"name":"弩箭_紫3级","model":["百恋_技能_千机弩"]},
{"id":12614,"name":"弩箭_紫4级","model":["百恋_技能_千机弩"]},
{"id":12615,"name":"弩箭_紫5级","model":["百恋_技能_千机弩"]},
{"id":12616,"name":"弩箭_紫_突破","model":["百恋_技能_孔雀翎"]},
{"id":12621,"name":"弩箭_红1级","model":["百恋_技能_千机弩"]},
{"id":12622,"name":"弩箭_红2级","model":["百恋_技能_千机弩"]},
{"id":12623,"name":"弩箭_红3级","model":["百恋_技能_千机弩"]},
{"id":12624,"name":"弩箭_红4级","model":["百恋_技能_千机弩"]},
{"id":12625,"name":"弩箭_红5级","model":["百恋_技能_千机弩"]},
{"id":12626,"name":"弩箭_红_突破","model":["百恋_技能_孔雀翎"]},
{"id":12631,"name":"棒球棍_蓝_1级","model":["百恋_技能_伏魔杖"]},
{"id":12632,"name":"棒球棍_蓝_2级","model":["百恋_技能_伏魔杖"]},
{"id":12633,"name":"棒球棍_蓝_3级","model":["百恋_技能_伏魔杖"]},
{"id":12634,"name":"棒球棍_蓝_4级","model":["百恋_技能_伏魔杖"]},
{"id":12635,"name":"棒球棍_蓝_5级","model":["百恋_技能_伏魔杖"]},
{"id":12636,"name":"棒球棍_蓝_突破","model":["百恋_技能_伏魔杖"]},
{"id":12641,"name":"棒球棍_紫_1级","model":["百恋_技能_伏魔杖"]},
{"id":12642,"name":"棒球棍_紫_2级","model":["百恋_技能_伏魔杖"]},
{"id":12643,"name":"棒球棍_紫_3级","model":["百恋_技能_伏魔杖"]},
{"id":12644,"name":"棒球棍_紫_4级","model":["百恋_技能_伏魔杖"]},
{"id":12645,"name":"棒球棍_紫_5级","model":["百恋_技能_伏魔杖"]},
{"id":12646,"name":"棒球棍_紫_突破","model":["百恋_技能_伏魔杖"]},
{"id":12651,"name":"棒球棍_红_1级","model":["百恋_技能_驱魔法棍"]},
{"id":12652,"name":"棒球棍_红_2级","model":["百恋_技能_驱魔法棍"]},
{"id":12653,"name":"棒球棍_红_3级","model":["百恋_技能_驱魔法棍"]},
{"id":12654,"name":"棒球棍_红_4级","model":["百恋_技能_驱魔法棍"]},
{"id":12655,"name":"棒球棍_红_5级","model":["百恋_技能_驱魔法棍"]},
{"id":12656,"name":"棒球棍_红_突破","model":["百恋_技能_驱魔法棍"]},
{"id":12701,"name":"虫壳外衣_子弹风暴","model":["百恋_装备技能_护盾冲击波_推开"]},
{"id":12711,"name":"犬牙项链_范围减速","model":["百恋_装备技能_范围减速"]},
{"id":12712,"name":"犬牙项链_范围减速_增强减速效果","model":["百恋_装备技能_范围减速"]},
{"id":12721,"name":"野兽腰带","model":[]},
{"id":12731,"name":"皮制手套","model":[]},
{"id":12741,"name":"兽爪战靴","model":[]},
{"id":12751,"name":"时尚夹克","model":[]},
{"id":12761,"name":"时尚项链","model":[]},
{"id":12771,"name":"时尚腰带","model":[]},
{"id":12781,"name":"时尚手套","model":[]},
{"id":12791,"name":"时尚皮靴","model":[]},
{"id":12801,"name":"厚重防护服_辐射脉冲","model":["百恋_装备技能_强力脉冲"]},
{"id":12802,"name":"厚重防护服_辐射脉冲_范围增加_附带击退","model":["百恋_装备技能_强力脉冲"]},
{"id":12811,"name":"原石项链_辐射圈_持续造成伤害","model":["百恋_装备技能_辐射圈2"]},
{"id":12812,"name":"原石项链_辐射圈_持续造成伤害_伤害翻倍","model":["百恋_装备技能_辐射圈2"]},
{"id":12821,"name":"厚重腰带_释放1次辐射脉冲","model":["百恋_装备技能_强力脉冲"]},
{"id":12822,"name":"厚重腰带_辐射脉冲伤害翻倍","model":["百恋_装备技能_强力脉冲"]},
{"id":12831,"name":"厚重手套_辐射圈","model":["百恋_装备技能_辐射圈"]},
{"id":12832,"name":"厚重手套_辐射圈_范围翻倍","model":["百恋_装备技能_辐射圈"]},
{"id":12841,"name":"厚重战靴_辐射圈","model":["百恋_装备技能_辐射圈"]},
{"id":12842,"name":"厚重战靴_辐射圈_范围翻倍","model":["百恋_装备技能_辐射圈"]},
{"id":12851,"name":"金属作战服","model":[]},
{"id":12861,"name":"能量项链","model":[]},
{"id":12871,"name":"能量腰带","model":[]},
{"id":12881,"name":"发光手套_小范围爆炸","model":["百恋_装备技能_小范围爆炸"]},
{"id":12882,"name":"发光手套_小范围爆炸_伤害翻倍","model":["百恋_装备技能_小范围爆炸"]},
{"id":12891,"name":"能量跑鞋","model":[]},
{"id":12892,"name":"军用作战服","model":[]},
{"id":12901,"name":"军用项链","model":[]},
{"id":12911,"name":"军用腰带_冲击波护盾","model":["百恋_装备技能_护盾冲击波"]},
{"id":12912,"name":"军用腰带_冲击波","model":["百恋_装备技能_护盾冲击波_推开"]},
{"id":12921,"name":"军用手套","model":[]},
{"id":12931,"name":"军用皮靴","model":[]},
{"id":12941,"name":"永恒战衣","model":[]},
{"id":12951,"name":"永恒项链","model":[]},
{"id":12961,"name":"永恒腰带","model":[]},
{"id":12971,"name":"永恒手套","model":[]},
{"id":12981,"name":"永恒战靴_火焰路径","model":["百恋_装备技能_火焰路径"]},
{"id":12981,"name":"永恒战靴_火焰路径_减速","model":["百恋_装备技能_火焰路径"]},
{"id":12991,"name":"破坏者风衣","model":[]},
{"id":13001,"name":"破坏者徽记","model":[]},
{"id":13011,"name":"破坏者束腰","model":[]},
{"id":13021,"name":"破坏者手甲_秒杀","model":["百恋_装备技能_秒杀"]},
{"id":13022,"name":"破坏者手甲_猩红光环","model":["百恋_装备技能_猩红光环"]},
{"id":13031,"name":"破坏者具足","model":[]},
{"id":1100010,"name":"镰刀攻击紫（远程）","model":["百恋_怪物子弹_回旋镰刀紫色"]},
{"id":1100011,"name":"镰刀攻击红（近战）","model":["百恋_怪物子弹_回旋镰刀红色"]},
{"id":1100012,"name":"镰刀攻击绿（分裂）小","model":["百恋_怪物子弹_回旋镰刀绿色"]},
{"id":1100013,"name":"电球紫分裂，中","model":["百恋_怪物子弹_通用电球紫色"]},
{"id":1100014,"name":"电球红分裂，大","model":["百恋_怪物子弹_通用电球红色"]},
{"id":1100015,"name":"电球蓝分裂，小","model":["百恋_怪物子弹_通用电球蓝色"]},
{"id":1100016,"name":"红毒眼弹","model":["百恋_怪物子弹_蜘蛛女王"]},
{"id":1100017,"name":"波动红眼弹","model":["百恋_装备技能_太刀刀光"]},
{"id":1100018,"name":"火焰护盾","model":["百恋_怪物子弹_火焰护盾"]},
{"id":1100019,"name":"雷霆冲击1","model":["百恋_怪物子弹_雷霆冲击"]},
{"id":1100020,"name":"雷霆冲击2","model":["百恋_怪物子弹_雷霆冲击"]},
{"id":1100021,"name":"雷霆冲击3","model":["百恋_怪物子弹_雷霆冲击"]},
{"id":1100022,"name":"灵魂冲击","model":["百恋_怪物子弹_封魔老妖"]},
{"id":1100023,"name":"灵魂冲击2","model":["百恋_怪物子弹_封魔老妖"]},
{"id":1100024,"name":"灵域之花","model":["百恋_怪物子弹_灵域之花"]},
{"id":1100025,"name":"龙炎爆破","model":["百恋_怪物子弹_龙炎爆破"]},
{"id":1100026,"name":"水聚弹","model":["百恋_怪物子弹_水聚弹"]},
{"id":1100027,"name":"水乱弹","model":["百恋_怪物子弹_水乱弹"]},
{"id":1100028,"name":"黑炎弹","model":["百恋_怪物子弹_黑炎弹"]},
{"id":1100029,"name":"黑炎弹2","model":["百恋_怪物子弹_黑炎弹"]},
{"id":1100030,"name":"寒水弹","model":["百恋_怪物子弹_寒水弹"]},
{"id":1100031,"name":"寒水弹2","model":["百恋_怪物子弹_寒水弹"]},
{"id":1100032,"name":"波动蓝球弹","model":["百恋_怪物子弹_千年蝠妖"]},
{"id":1100033,"name":"波动绿球弹","model":["百恋_怪物子弹_战俘僵尸"]},
{"id":1100034,"name":"水球","model":["百恋_怪物子弹_水球"]},
{"id":1100035,"name":"火球","model":["百恋_怪物子弹_火球"]},
{"id":1100036,"name":"突刺紫","model":["百恋_怪物子弹_突刺紫"]},
{"id":1100037,"name":"突刺绿","model":["百恋_怪物子弹_突刺绿"]},
{"id":1100038,"name":"突刺黄","model":["百恋_怪物子弹_突刺黄"]},
{"id":1100039,"name":"突刺红","model":["百恋_怪物子弹_突刺红"]},
{"id":1100040,"name":"波动弹黄色","model":["百恋_怪物子弹_蜘蛛女王"]},
{"id":1100041,"name":"风球","model":["百恋_怪物子弹_风球"]},
{"id":1100042,"name":"绿毒眼弹","model":["百恋_怪物子弹_绿毒眼弹"]},
{"id":1100043,"name":"波动弹绿色","model":["百恋_怪物子弹_鬼妖蜘蛛"]},
{"id":1100044,"name":"波动弹紫色","model":["百恋_怪物子弹_蜘蛛女王"]},
{"id":1100045,"name":"红毒眼弹","model":["百恋_装备技能_太刀刀光"]},
{"id":1100046,"name":"红毒眼弹","model":["百恋_装备技能_太刀刀光"]},
{"id":1100047,"name":"红毒眼弹","model":["百恋_装备技能_太刀刀光"]},
{"id":1100048,"name":"红毒眼弹","model":["百恋_装备技能_太刀刀光"]},
{"id":13101,"name":"火神符","model":["战斗_战斗场景特效_火神符"]}]