[
  {"id":"1","name":"海星","leibie":4,"pinzhi":1,"kinds":[401,407],"changdu":[3.5,14],"dyAt":[1,2],"eps":{"xixue":500},"qiangdu":8,"suoshu":[1,2,3,4,5],"limit":0,"prob":5000,"chushou":[1,907,6]},
  {"id":"2","name":"海胆","leibie":4,"pinzhi":1,"kinds":[401,431],"changdu":[2.5,10],"dyAt":[1,2],"eps":{"fanji":500},"qiangdu":8,"suoshu":[1,2,3,4,5],"limit":0,"prob":5000,"chushou":[1,907,6]},
  {"id":"3","name":"骨头鱼","leibie":1,"pinzhi":6,"kinds":[101,103,540],"changdu":[40,160],"dyAt":[2,4],"eps":{"atk":2200,"def":700},"qiangdu":30,"suoshu":[1,2,3,4,5],"limit":1001,"prob":1000,"chushou":[1,907,80]},
  {"id":"4","name":"青蛙","leibie":4,"pinzhi":2,"kinds":[401,433],"changdu":[6,24],"dyAt":[1,2],"eps":{"lianji":500},"qiangdu":8,"suoshu":[1,2,3,4,5],"limit":0,"prob":2400,"chushou":[1,907,10]},
  {"id":"5","name":"河豚","leibie":1,"pinzhi":3,"kinds":[101,141],"changdu":[15,60],"dyAt":[1,2],"eps":{"atk":1760,"def":560},"qiangdu":8,"suoshu":[1,2,3,4,5],"limit":0,"prob":3000,"chushou":[1,907,15]},
  {"id":"6","name":"蚌","leibie":4,"pinzhi":2,"kinds":[401,435],"changdu":[10,40],"dyAt":[1,2],"eps":{"fanji":575},"qiangdu":8,"suoshu":[1,2,3,4,5,6,7],"limit":0,"prob":800,"chushou":[1,909,2]},
  {"id":"7","name":"蜗牛","leibie":4,"pinzhi":3,"kinds":[401,437],"changdu":[2,8],"dyAt":[1,2],"eps":{"def":560,"fanji":575},"qiangdu":9,"suoshu":[1,2,3,4,5],"limit":0,"prob":1800,"chushou":[1,907,15]},
  {"id":"8","name":"虾","leibie":4,"pinzhi":1,"kinds":[401,439],"changdu":[8,32],"dyAt":[1,2],"eps":{"shanbi":500},"qiangdu":8,"suoshu":[1,2,3,4,5],"limit":0,"prob":3000,"chushou":[1,907,4]},
  {"id":"9","name":"鲈鱼","leibie":2,"pinzhi":1,"kinds":[201,209],"changdu":[25,100],"dyAt":[1,2],"eps":{"hsshanbi":250,"hsxixue":250},"qiangdu":8,"suoshu":[1,2,3,4,5],"limit":0,"prob":5000,"chushou":[1,907,7]},
  {"id":"10","name":"鲫鱼","leibie":2,"pinzhi":1,"kinds":[201,231],"changdu":[13,52],"dyAt":[1,2],"eps":{"hslianji":500},"qiangdu":8,"suoshu":[1,2,3,4,5],"limit":0,"prob":5000,"chushou":[1,907,4]},
  {"id":"11","name":"草鱼","leibie":2,"pinzhi":1,"kinds":[201,267],"changdu":[25,100],"dyAt":[1,2],"eps":{"hsfanji":500},"qiangdu":8,"suoshu":[1,2,3,4,5],"limit":0,"prob":5000,"chushou":[1,907,4]},
  {"id":"12","name":"金鱼","leibie":1,"pinzhi":1,"kinds":[101,143],"changdu":[15,60],"dyAt":[1,2],"eps":{"hp_max":5600},"qiangdu":8,"suoshu":[1,2,3,4,5],"limit":0,"prob":5000,"chushou":[1,907,6]},
  {"id":"13","name":"泥鳅","leibie":1,"pinzhi":2,"kinds":[101,145],"changdu":[15,60],"dyAt":[1,2],"eps":{"hp_max":4800,"def":420},"qiangdu":8,"suoshu":[1,2,3,4,5],"limit":0,"prob":5000,"chushou":[1,907,10]},
  {"id":"14","name":"鲶鱼","leibie":2,"pinzhi":2,"kinds":[201,273],"changdu":[50,200],"dyAt":[1,2],"eps":{"hsbaoji":280,"hsjiyun":280},"qiangdu":8,"suoshu":[1,2,3,4,5],"limit":0,"prob":5000,"chushou":[1,907,10]},
  {"id":"15","name":"沙丁鱼","leibie":1,"pinzhi":1,"kinds":[101,109],"changdu":[15,60],"dyAt":[1,2],"eps":{"atk":1540},"qiangdu":8,"suoshu":[1,2,3,4,5],"limit":0,"prob":5000,"chushou":[1,907,5]},
  {"id":"16","name":"月光水母","leibie":4,"pinzhi":4,"kinds":[401,441],"changdu":[35,140],"dyAt":[2,4],"eps":{"speed":240,"jiyun":700},"qiangdu":31,"suoshu":[1],"limit":0,"prob":800,"chushou":[1,907,24]},
  {"id":"17","name":"海龟","leibie":4,"pinzhi":2,"kinds":[401,443],"changdu":[60,240],"dyAt":[1,2],"eps":{"jiyun":580},"qiangdu":8,"suoshu":[1],"limit":0,"prob":2400,"chushou":[1,907,12]},
  {"id":"18","name":"鳄龟","leibie":4,"pinzhi":3,"kinds":[401,445],"changdu":[80,320],"dyAt":[1,2],"eps":{"baoji":650},"qiangdu":19,"suoshu":[1],"limit":0,"prob":1800,"chushou":[1,907,18]},
  {"id":"19","name":"海马","leibie":4,"pinzhi":2,"kinds":[401,409],"changdu":[4,16],"dyAt":[1,2],"eps":{"shanbi":580},"qiangdu":8,"suoshu":[1,2,3,4,5],"limit":0,"prob":2400,"chushou":[1,907,12]},
  {"id":"20","name":"锦鲤","leibie":2,"pinzhi":6,"kinds":[201,275,540],"changdu":[24,96],"dyAt":[4,10],"eps":{"hsbaoji":320,"hslianji":320},"qiangdu":42,"suoshu":[1],"limit":0,"prob":1000,"chushou":[1,907,30]},
  {"id":"21","name":"巨嘴鱼","leibie":3,"pinzhi":2,"kinds":[301,305],"changdu":[125,500],"dyAt":[1,2],"eps":{"atk_per":700},"qiangdu":8,"suoshu":[1],"limit":0,"prob":1000,"chushou":[1,907,12]},
  {"id":"22","name":"西太公鱼","leibie":1,"pinzhi":3,"kinds":[101,147],"changdu":[11,44],"dyAt":[1,2],"eps":{"hp_max":6400,"atk":1760},"qiangdu":19,"suoshu":[1],"limit":0,"prob":3000,"chushou":[1,907,18]},
  {"id":"23","name":"香鱼","leibie":2,"pinzhi":3,"kinds":[201,277],"changdu":[15,60],"dyAt":[1,2],"eps":{"hsshanbi":300,"hsjiyun":300},"qiangdu":19,"suoshu":[1],"limit":0,"prob":3000,"chushou":[1,907,18]},
  {"id":"24","name":"霓虹鱼","leibie":1,"pinzhi":6,"kinds":[101,149,540],"changdu":[3,12],"dyAt":[2,4],"eps":{"speed":240,"def":720},"qiangdu":42,"suoshu":[1],"limit":0,"prob":800,"chushou":[1,907,30]},
  {"id":"25","name":"多鳍鱼","leibie":3,"pinzhi":3,"kinds":[301,319],"changdu":[70,280],"dyAt":[1,2],"eps":{"atk_per":500,"def_per":500},"qiangdu":8,"suoshu":[1],"limit":0,"prob":1200,"chushou":[1,907,18]},
  {"id":"26","name":"条石鲷","leibie":2,"pinzhi":2,"kinds":[201,279],"changdu":[20,80],"dyAt":[1,2],"eps":{"hslianji":580},"qiangdu":8,"suoshu":[1],"limit":0,"prob":4000,"chushou":[1,907,12]},
  {"id":"27","name":"蓝环章鱼","leibie":4,"pinzhi":4,"kinds":[401,411],"changdu":[15,60],"dyAt":[2,4],"eps":{"baoji":400,"jiyun":400},"qiangdu":44,"suoshu":[2],"limit":0,"prob":1200,"chushou":[1,907,46]},
  {"id":"28","name":"蝾螈","leibie":4,"pinzhi":4,"kinds":[401,413],"changdu":[25,100],"dyAt":[2,4],"eps":{"xixue":400,"shanbi":400},"qiangdu":44,"suoshu":[2],"limit":0,"prob":1200,"chushou":[1,907,43]},
  {"id":"29","name":"翻车鱼","leibie":3,"pinzhi":6,"kinds":[301,321,540],"changdu":[150,600],"dyAt":[2,4],"eps":{"hp_max":9750,"atk_per":900},"qiangdu":58,"suoshu":[2],"limit":0,"prob":500,"chushou":[1,907,56]},
  {"id":"30","name":"骨舌鱼","leibie":3,"pinzhi":6,"kinds":[301,323,540],"changdu":[150,600],"dyAt":[2,4],"eps":{"hp_max":9750,"def_per":900},"qiangdu":58,"suoshu":[2],"limit":0,"prob":500,"chushou":[1,907,54]},
  {"id":"31","name":"小丑鱼","leibie":1,"pinzhi":3,"kinds":[101,151],"changdu":[6,24],"dyAt":[1,2],"eps":{"atk":1944,"def":644},"qiangdu":30,"suoshu":[2],"limit":0,"prob":3000,"chushou":[1,907,31]},
  {"id":"32","name":"狮子鱼","leibie":1,"pinzhi":3,"kinds":[101,153],"changdu":[18,72],"dyAt":[1,2],"eps":{"hp_max":7800,"atk":1944},"qiangdu":30,"suoshu":[2],"limit":0,"prob":3000,"chushou":[1,907,34]},
  {"id":"33","name":"比目鱼","leibie":2,"pinzhi":3,"kinds":[201,281],"changdu":[80,320],"dyAt":[1,2],"eps":{"hsshanbi":330,"hsfanji":330},"qiangdu":30,"suoshu":[2],"limit":0,"prob":3000,"chushou":[1,907,32]},
  {"id":"34","name":"褐色岩鱼","leibie":2,"pinzhi":3,"kinds":[201,283],"changdu":[15,60],"dyAt":[1,2],"eps":{"hsjiyun":330,"hsxixue":330},"qiangdu":30,"suoshu":[2],"limit":0,"prob":3000,"chushou":[1,907,35]},
  {"id":"35","name":"石头鱼","leibie":1,"pinzhi":3,"kinds":[101,111],"changdu":[17,68],"dyAt":[1,2],"eps":{"hp_max":7800,"def":644},"qiangdu":30,"suoshu":[2],"limit":0,"prob":3000,"chushou":[1,907,34]},
  {"id":"36","name":"胭脂鱼","leibie":2,"pinzhi":3,"kinds":[201,211],"changdu":[33,132],"dyAt":[1,2],"eps":{"hsbaoji":330,"hslianji":330},"qiangdu":30,"suoshu":[2],"limit":0,"prob":3000,"chushou":[1,907,37]},
  {"id":"37","name":"鳄鱼","leibie":4,"pinzhi":6,"kinds":[401,436,540],"changdu":[125,500],"dyAt":[3,6],"eps":{"lianji":450,"baoji":450},"qiangdu":58,"suoshu":[2],"limit":1004,"prob":600,"chushou":[1,907,160]},
  {"id":"38","name":"寄居蟹","leibie":4,"pinzhi":2,"kinds":[401,415],"changdu":[3,12],"dyAt":[1,2],"eps":{"xixue":390,"lianji":390},"qiangdu":42,"suoshu":[3],"limit":0,"prob":2400,"chushou":[1,907,27]},
  {"id":"39","name":"大龙虾","leibie":4,"pinzhi":4,"kinds":[401,417],"changdu":[11,44],"dyAt":[2,4],"eps":{"xixue":460,"baoji":460},"qiangdu":60,"suoshu":[3],"limit":0,"prob":1200,"chushou":[1,907,54]},
  {"id":"40","name":"鲑鱼","leibie":2,"pinzhi":3,"kinds":[201,213],"changdu":[42,168],"dyAt":[1,2],"eps":{"hsshanbi":420,"hsxixue":420},"qiangdu":51,"suoshu":[3],"limit":0,"prob":2000,"chushou":[1,907,40]},
  {"id":"41","name":"孔雀鱼","leibie":1,"pinzhi":4,"kinds":[101,113],"changdu":[2,8],"dyAt":[2,4],"eps":{"atk":2394,"def":828},"qiangdu":60,"suoshu":[3],"limit":0,"prob":2000,"chushou":[1,907,54]},
  {"id":"42","name":"神仙鱼","leibie":1,"pinzhi":4,"kinds":[101,115],"changdu":[4,16],"dyAt":[2,4],"eps":{"hp_max":10350,"atk":2394},"qiangdu":60,"suoshu":[3],"limit":0,"prob":2000,"chushou":[1,907,54]},
  {"id":"43","name":"蝴蝶鱼","leibie":1,"pinzhi":4,"kinds":[101,117],"changdu":[1.5,6],"dyAt":[2,4],"eps":{"hp_max":10350,"def":828},"qiangdu":60,"suoshu":[3],"limit":0,"prob":2000,"chushou":[1,907,54]},
  {"id":"44","name":"鲷鱼","leibie":2,"pinzhi":2,"kinds":[201,215],"changdu":[18,72],"dyAt":[1,2],"eps":{"hsshanbi":390,"hsfanji":390},"qiangdu":42,"suoshu":[3],"limit":0,"prob":2000,"chushou":[1,907,27]},
  {"id":"45","name":"罗非鱼","leibie":2,"pinzhi":2,"kinds":[201,217],"changdu":[15,60],"dyAt":[1,2],"eps":{"hsjiyun":390,"hslianji":390},"qiangdu":42,"suoshu":[3],"limit":0,"prob":5000,"chushou":[1,907,27]},
  {"id":"46","name":"太阳鱼","leibie":2,"pinzhi":2,"kinds":[201,219],"changdu":[13,52],"dyAt":[1,2],"eps":{"hsfanji":390,"hslianji":390},"qiangdu":42,"suoshu":[3],"limit":0,"prob":5000,"chushou":[1,907,27]},
  {"id":"47","name":"凤尾鱼","leibie":1,"pinzhi":3,"kinds":[101,119],"changdu":[3,12],"dyAt":[1,2],"eps":{"speed":360,"atk":2128},"qiangdu":51,"suoshu":[3],"limit":0,"prob":3000,"chushou":[1,907,40]},
  {"id":"48","name":"鳝鱼","leibie":2,"pinzhi":3,"kinds":[201,221],"changdu":[25,100],"dyAt":[1,2],"eps":{"hsshanbi":400,"hsbaoji":400},"qiangdu":51,"suoshu":[3],"limit":0,"prob":3000,"chushou":[1,907,40]},
  {"id":"49","name":"五彩鳗","leibie":2,"pinzhi":3,"kinds":[201,223],"changdu":[36,144],"dyAt":[1,2],"eps":{"hsbaoji":400,"hsfanji":400},"qiangdu":51,"suoshu":[3],"limit":0,"prob":3000,"chushou":[1,907,40]},
  {"id":"50","name":"旗鱼","leibie":3,"pinzhi":6,"kinds":[301,328,540],"changdu":[140,560],"dyAt":[2,4],"eps":{"speed":360,"atk_per":1000},"qiangdu":68,"suoshu":[3],"limit":0,"prob":1000,"chushou":[1,907,67]},
  {"id":"51","name":"鬼头刀","leibie":3,"pinzhi":4,"kinds":[301,325],"changdu":[34,136],"dyAt":[2,4],"eps":{"atk":2394,"def_per":900},"qiangdu":60,"suoshu":[3],"limit":0,"prob":1000,"chushou":[1,907,54]},
  {"id":"52","name":"鳐鱼","leibie":3,"pinzhi":4,"kinds":[301,327],"changdu":[44,176],"dyAt":[2,4],"eps":{"def":828,"hp_max_per":900},"qiangdu":60,"suoshu":[3],"limit":0,"prob":1000,"chushou":[1,907,54]},
  {"id":"53","name":"双髻鲨","leibie":3,"pinzhi":6,"kinds":[301,326,540],"changdu":[130,520],"dyAt":[2,4],"eps":{"def":920,"atk_per":1000},"qiangdu":68,"suoshu":[3],"limit":1015,"prob":1000,"chushou":[1,907,200]},
  {"id":"54","name":"矛尾鱼","leibie":3,"pinzhi":3,"kinds":[301,329],"changdu":[134,536],"dyAt":[1,2],"eps":{"atk":2128,"hp_max_per":800},"qiangdu":51,"suoshu":[3],"limit":0,"prob":1000,"chushou":[1,907,40]},
  {"id":"55","name":"石斑鱼","leibie":2,"pinzhi":2,"kinds":[201,225],"changdu":[20,80],"dyAt":[1,2],"eps":{"hsshanbi":390,"hsfanji":390},"qiangdu":42,"suoshu":[3],"limit":0,"prob":5000,"chushou":[1,907,27]},
  {"id":"56","name":"金枪鱼","leibie":2,"pinzhi":2,"kinds":[201,227],"changdu":[68,272],"dyAt":[1,2],"eps":{"hsjiyun":390,"hsfanji":390},"qiangdu":42,"suoshu":[3],"limit":0,"prob":5000,"chushou":[1,907,27]},
  {"id":"57","name":"三文鱼","leibie":2,"pinzhi":2,"kinds":[201,229],"changdu":[21,84],"dyAt":[1,2],"eps":{"hsfanji":390,"hsxixue":390},"qiangdu":42,"suoshu":[3],"limit":0,"prob":5000,"chushou":[1,907,27]},
  {"id":"58","name":"虎鲨","leibie":3,"pinzhi":6,"kinds":[301,307,540],"changdu":[160,640],"dyAt":[2,4],"eps":{"atk":2660,"atk_per":1000},"qiangdu":68,"suoshu":[3],"limit":0,"prob":800,"chushou":[1,907,67]},
  {"id":"59","name":"白海豚","leibie":4,"pinzhi":6,"kinds":[401,446,540],"changdu":[76,304],"dyAt":[2,4],"eps":{"shanbi":500,"baoji":500},"qiangdu":68,"suoshu":[3],"limit":1005,"prob":600,"chushou":[1,907,200]},
  {"id":"60","name":"鳕鱼","leibie":2,"pinzhi":4,"kinds":[201,233],"changdu":[25,100],"dyAt":[2,4],"eps":{"hsjiyun":460,"hsxixue":460},"qiangdu":60,"suoshu":[3],"limit":0,"prob":2000,"chushou":[1,907,54]},
  {"id":"61","name":"大王乌贼","leibie":4,"pinzhi":6,"kinds":[401,540],"changdu":[300,1200],"dyAt":[2,4],"eps":{"shanbi":500,"jiyun":500},"qiangdu":68,"suoshu":[3],"limit":0,"prob":600,"chushou":[1,907,67]},
  {"id":"62","name":"小龙虾","leibie":4,"pinzhi":2,"kinds":[401,419],"changdu":[5,20],"dyAt":[1,2],"eps":{"fanji":300,"baoji":560},"qiangdu":55,"suoshu":[4],"limit":0,"prob":2400,"chushou":[1,907,50]},
  {"id":"63","name":"蜘蛛蟹","leibie":4,"pinzhi":3,"kinds":[401,423],"changdu":[100,400],"dyAt":[1,2],"eps":{"lianji":300,"shanbi":640},"qiangdu":66,"suoshu":[4],"limit":0,"prob":1800,"chushou":[1,907,75]},
  {"id":"64","name":"海参","leibie":4,"pinzhi":3,"kinds":[401,427],"changdu":[8,32],"dyAt":[1,2],"eps":{"xixue":300,"jiyun":640},"qiangdu":66,"suoshu":[4],"limit":0,"prob":1800,"chushou":[1,907,75]},
  {"id":"65","name":"黑鱼","leibie":2,"pinzhi":2,"kinds":[201,235],"changdu":[35,140],"dyAt":[1,2],"eps":{"hsjiyun":370,"hsfanji":440},"qiangdu":55,"suoshu":[4],"limit":0,"prob":4000,"chushou":[1,907,50]},
  {"id":"66","name":"白斑狗鱼","leibie":2,"pinzhi":3,"kinds":[201,239],"changdu":[45,180],"dyAt":[1,2],"eps":{"hsshanbi":400,"hsxixue":520},"qiangdu":66,"suoshu":[4],"limit":0,"prob":3000,"chushou":[1,907,75]},
  {"id":"67","name":"金鳟","leibie":2,"pinzhi":3,"kinds":[201,243],"changdu":[38,152],"dyAt":[1,2],"eps":{"hsbaoji":400,"hsjiyun":520},"qiangdu":66,"suoshu":[4],"limit":0,"prob":3000,"chushou":[1,907,75]},
  {"id":"68","name":"哲罗鱼","leibie":3,"pinzhi":3,"kinds":[301,309],"changdu":[95,380],"dyAt":[1,2],"eps":{"def":828,"def_per":880},"qiangdu":66,"suoshu":[4],"limit":0,"prob":1000,"chushou":[1,907,75]},
  {"id":"69","name":"斗鱼","leibie":1,"pinzhi":4,"kinds":[101,121],"changdu":[4,16],"dyAt":[2,4],"eps":{"speed":378,"hp_max":11925},"qiangdu":77,"suoshu":[4],"limit":0,"prob":2000,"chushou":[1,907,100]},
  {"id":"70","name":"电鳗","leibie":3,"pinzhi":6,"kinds":[301,313,540],"changdu":[82,328],"dyAt":[2,4],"eps":{"hp_max_per":300,"atk_per":800},"qiangdu":88,"suoshu":[4],"limit":0,"prob":800,"chushou":[1,907,125]},
  {"id":"71","name":"食人鱼","leibie":1,"pinzhi":6,"kinds":[101,540],"changdu":[8.5,34],"dyAt":[2,4],"eps":{"speed":480,"atk":3350},"qiangdu":88,"suoshu":[4],"limit":1006,"prob":1000,"chushou":[1,907,240]},
  {"id":"72","name":"刺尾鲷鱼","leibie":1,"pinzhi":4,"kinds":[101,123],"changdu":[11,44],"dyAt":[2,4],"eps":{"hp_max":11925,"atk":2601},"qiangdu":77,"suoshu":[4],"limit":0,"prob":2000,"chushou":[1,907,100]},
  {"id":"73","name":"蓝唇鱼","leibie":1,"pinzhi":1,"kinds":[101,125],"changdu":[6,24],"dyAt":[1,2],"eps":{"hp_max":7950,"def":642},"qiangdu":44,"suoshu":[4],"limit":0,"prob":5000,"chushou":[1,907,25]},
  {"id":"74","name":"帝王蟹","leibie":4,"pinzhi":6,"kinds":[401,540],"changdu":[55,220],"dyAt":[3,7],"eps":{"fanji":500,"lianji":720},"qiangdu":91,"suoshu":[5],"limit":1009,"prob":500,"chushou":[1,907,288]},
  {"id":"75","name":"鲟鱼","leibie":2,"pinzhi":4,"kinds":[201,247],"changdu":[60,240],"dyAt":[3,7],"eps":{"hsshanbi":450,"hsjiyun":590},"qiangdu":81,"suoshu":[5],"limit":0,"prob":2000,"chushou":[1,907,112]},
  {"id":"76","name":"花鲢鱼","leibie":2,"pinzhi":2,"kinds":[201,249],"changdu":[37,148],"dyAt":[1,2],"eps":{"hsjiyun":400,"hslianji":440},"qiangdu":59,"suoshu":[5],"limit":0,"prob":4000,"chushou":[1,907,56]},
  {"id":"77","name":"鮟鱇鱼","leibie":2,"pinzhi":4,"kinds":[201,253],"changdu":[22,88],"dyAt":[3,7],"eps":{"hsbaoji":450,"hsjiyun":590},"qiangdu":81,"suoshu":[5],"limit":0,"prob":2000,"chushou":[1,907,112]},
  {"id":"78","name":"肿头鱼","leibie":2,"pinzhi":3,"kinds":[201,255],"changdu":[24,96],"dyAt":[1,2],"eps":{"hsfanji":430,"hslianji":500},"qiangdu":70,"suoshu":[5],"limit":0,"prob":3000,"chushou":[1,907,84]},
  {"id":"79","name":"蝠鲼","leibie":3,"pinzhi":4,"kinds":[301,315],"changdu":[144,576],"dyAt":[3,7],"eps":{"hp_max":13500,"hp_max_per":960},"qiangdu":81,"suoshu":[5],"limit":0,"prob":1000,"chushou":[1,907,112]},
  {"id":"80","name":"鲸鲨","leibie":3,"pinzhi":6,"kinds":[301,317,540],"changdu":[450,1800],"dyAt":[3,7],"eps":{"hp_max_per":400,"atk_per":800},"qiangdu":91,"suoshu":[5],"limit":0,"prob":800,"chushou":[1,907,140]},
  {"id":"81","name":"皇带鱼","leibie":2,"pinzhi":3,"kinds":[201,259],"changdu":[345,1380],"dyAt":[1,2],"eps":{"hslianji":430,"hsxixue":500},"qiangdu":70,"suoshu":[5],"limit":0,"prob":3000,"chushou":[1,907,84]},
  {"id":"82","name":"吸盘鱼","leibie":1,"pinzhi":3,"kinds":[101,127],"changdu":[13,52],"dyAt":[1,2],"eps":{"hp_max":12000,"def":920},"qiangdu":70,"suoshu":[5],"limit":0,"prob":3000,"chushou":[1,907,84]},
  {"id":"83","name":"狗鱼","leibie":2,"pinzhi":3,"kinds":[201,263],"changdu":[31,124],"dyAt":[1,2],"eps":{"hsbaoji":430,"hsxixue":500},"qiangdu":70,"suoshu":[5],"limit":0,"prob":3000,"chushou":[1,907,84]},
  {"id":"84","name":"鲱鱼","leibie":2,"pinzhi":2,"kinds":[201,269],"changdu":[19,76],"dyAt":[1,2],"eps":{"hsshanbi":400,"hsfanji":440},"qiangdu":59,"suoshu":[5],"limit":0,"prob":4000,"chushou":[1,907,56]},
  {"id":"85","name":"竹荚鱼","leibie":1,"pinzhi":1,"kinds":[101,131],"changdu":[11,44],"dyAt":[1,2],"eps":{"atk":2184,"def":805},"qiangdu":49,"suoshu":[5],"limit":0,"prob":5000,"chushou":[1,907,28]},
  {"id":"86","name":"飞鱼","leibie":1,"pinzhi":3,"kinds":[101,137],"changdu":[14,56],"dyAt":[1,2],"eps":{"speed":384,"def":920},"qiangdu":70,"suoshu":[5],"limit":0,"prob":3000,"chushou":[1,907,84]},
  {"id":"87","name":"树枝","leibie":5,"pinzhi":1,"kinds":[501,504],"changdu":[0,0],"dyAt":[1,2],"eps":null,"qiangdu":1,"suoshu":[1,2,3],"limit":0,"prob":2500,"chushou":[1,907,1]},
  {"id":"88","name":"断剑","leibie":5,"pinzhi":1,"kinds":[501,513],"changdu":[0,0],"dyAt":[1,2],"eps":null,"qiangdu":1,"suoshu":[1,2,3],"limit":0,"prob":2500,"chushou":[1,907,2]},
  {"id":"89","name":"水草","leibie":5,"pinzhi":1,"kinds":[501,516],"changdu":[0,0],"dyAt":[1,2],"eps":null,"qiangdu":1,"suoshu":[1,2,3],"limit":0,"prob":2500,"chushou":[1,907,3]},
  {"id":"90","name":"破旧道袍","leibie":5,"pinzhi":1,"kinds":[501,519],"changdu":[0,0],"dyAt":[1,2],"eps":null,"qiangdu":1,"suoshu":[1,2,3],"limit":0,"prob":2500,"chushou":[1,907,1]},
  {"id":"91","name":"空宝箱","leibie":5,"pinzhi":1,"kinds":[501,522],"changdu":[0,0],"dyAt":[1,2],"eps":null,"qiangdu":1,"suoshu":[1,2,3],"limit":0,"prob":2500,"chushou":[1,907,2]},
  {"id":"92","name":"咸鱼","leibie":5,"pinzhi":1,"kinds":[501,525],"changdu":[0,0],"dyAt":[1,2],"eps":null,"qiangdu":1,"suoshu":[1,2,3],"limit":0,"prob":2500,"chushou":[1,907,1]},
  {"id":"93","name":"金条","leibie":5,"pinzhi":3,"kinds":[501],"changdu":[0,0],"dyAt":[1,2],"eps":null,"qiangdu":1,"suoshu":[1,2,3],"limit":0,"prob":1500,"chushou":[1,907,36]},
  {"id":"94","name":"东海明珠","leibie":5,"pinzhi":6,"kinds":[501],"changdu":[0,0],"dyAt":[1,2],"eps":null,"qiangdu":1,"suoshu":[1,2,3],"limit":0,"prob":500,"chushou":[1,907,70]},
  {"id":"95","name":"《盟主》","leibie":5,"pinzhi":6,"kinds":[501],"changdu":[0,0],"dyAt":[1,2],"eps":null,"qiangdu":1,"suoshu":[1,2,3],"limit":1016,"prob":500,"chushou":[1,907,80]},
  {"id":"96","name":"古董花瓶","leibie":5,"pinzhi":4,"kinds":[501],"changdu":[0,0],"dyAt":[1,2],"eps":null,"qiangdu":1,"suoshu":[1,2,3],"limit":0,"prob":1000,"chushou":[1,907,50]},
  {"id":"97","name":"红宝石","leibie":5,"pinzhi":6,"kinds":[501,540],"changdu":[0,0],"dyAt":[1,2],"eps":null,"qiangdu":1,"suoshu":[1,2,3],"limit":1016,"prob":1000,"chushou":[1,907,180]},
  {"id":"98","name":"珊瑚","leibie":5,"pinzhi":2,"kinds":[501,507],"changdu":[0,0],"dyAt":[1,2],"eps":null,"qiangdu":1,"suoshu":[1,2,3],"limit":0,"prob":2000,"chushou":[1,907,25]},
  {"id":"99","name":"贝壳","leibie":5,"pinzhi":2,"kinds":[501,510],"changdu":[0,0],"dyAt":[1,2],"eps":null,"qiangdu":1,"suoshu":[1,2,3],"limit":0,"prob":2000,"chushou":[1,907,20]},
  {"id":"100","name":"腐烂的植物","leibie":5,"pinzhi":1,"kinds":[501],"changdu":[0,0],"dyAt":[1,2],"eps":null,"qiangdu":1,"suoshu":[1,2,3],"limit":0,"prob":2500,"chushou":[1,907,2]},
  {"id":"101","name":"遗落玉玺","leibie":5,"pinzhi":6,"kinds":[501],"changdu":[0,0],"dyAt":[1,2],"eps":null,"qiangdu":1,"suoshu":[4,5,6,7,8,9],"limit":1016,"prob":100,"chushou":[1,907,1888]},
  {"id":"102","name":"《相忘江湖》","leibie":5,"pinzhi":6,"kinds":[501],"changdu":[0,0],"dyAt":[1,2],"eps":null,"qiangdu":1,"suoshu":[4,5],"limit":1016,"prob":500,"chushou":[1,907,80]},
  {"id":"103","name":"冰魄镖","leibie":5,"pinzhi":6,"kinds":[501],"changdu":[0,0],"dyAt":[1,2],"eps":null,"qiangdu":1,"suoshu":[4,5,6,7,8,9],"limit":1016,"prob":2000,"chushou":[1,907,360]},
  {"id":"104","name":"银鳞镖","leibie":5,"pinzhi":4,"kinds":[501],"changdu":[0,0],"dyAt":[1,2],"eps":null,"qiangdu":1,"suoshu":[4,5,6,7,8,9],"limit":1016,"prob":3000,"chushou":[1,907,240]},
  {"id":"105","name":"金钱镖","leibie":5,"pinzhi":3,"kinds":[501],"changdu":[0,0],"dyAt":[1,2],"eps":null,"qiangdu":1,"suoshu":[4,5,6,7,8,9],"limit":1016,"prob":4000,"chushou":[1,907,120]},
  {"id":"106","name":"靴子","leibie":5,"pinzhi":1,"kinds":[501,104],"changdu":[0,0],"dyAt":[1,2],"eps":null,"qiangdu":1,"suoshu":[4,5,6,7],"limit":0,"prob":5000,"chushou":[1,907,26]},
  {"id":"107","name":"破旧道袍","leibie":5,"pinzhi":1,"kinds":[501,519],"changdu":[0,0],"dyAt":[1,2],"eps":null,"qiangdu":1,"suoshu":[4,5,6,7],"limit":0,"prob":5000,"chushou":[1,907,26]},
  {"id":"108","name":"仙剑碎片","leibie":5,"pinzhi":3,"kinds":[501],"changdu":[0,0],"dyAt":[1,2],"eps":null,"qiangdu":1,"suoshu":[4,5,6,7],"limit":0,"prob":3000,"chushou":[1,907,66]},
  {"id":"109","name":"鱼竿","leibie":5,"pinzhi":2,"kinds":[501],"changdu":[0,0],"dyAt":[1,2],"eps":null,"qiangdu":1,"suoshu":[4,5,6,7],"limit":0,"prob":4000,"chushou":[1,907,38]},
  {"id":"110","name":"乌龙皓石","leibie":5,"pinzhi":3,"kinds":[501],"changdu":[0,0],"dyAt":[1,2],"eps":null,"qiangdu":1,"suoshu":[6,7,8,9],"limit":1016,"prob":500,"chushou":[1,909,12]},
  {"id":"111","name":"高昌秘宝","leibie":5,"pinzhi":4,"kinds":[501],"changdu":[0,0],"dyAt":[1,2],"eps":null,"qiangdu":1,"suoshu":[6],"limit":1016,"prob":80,"chushou":[1,1,666]},
  {"id":"112","name":"高昌秘宝","leibie":5,"pinzhi":4,"kinds":[501],"changdu":[0,0],"dyAt":[1,2],"eps":null,"qiangdu":1,"suoshu":[7],"limit":1016,"prob":80,"chushou":[1,2,7000]},
  {"id":"114","name":"《开端》","leibie":5,"pinzhi":3,"kinds":[501],"changdu":[0,0],"dyAt":[1,2],"eps":null,"qiangdu":1,"suoshu":[1],"limit":1016,"prob":500,"chushou":[1,907,80]},
  {"id":"115","name":"《刺客之剑》","leibie":5,"pinzhi":4,"kinds":[501],"changdu":[0,0],"dyAt":[1,2],"eps":null,"qiangdu":1,"suoshu":[1],"limit":1016,"prob":200,"chushou":[1,907,160]},
  {"id":"116","name":"《迷踪林》","leibie":5,"pinzhi":3,"kinds":[501],"changdu":[0,0],"dyAt":[1,2],"eps":null,"qiangdu":1,"suoshu":[2],"limit":1016,"prob":180,"chushou":[1,907,160]},
  {"id":"117","name":"《凛冽北风》","leibie":5,"pinzhi":4,"kinds":[501],"changdu":[0,0],"dyAt":[1,2],"eps":null,"qiangdu":1,"suoshu":[2],"limit":1016,"prob":80,"chushou":[1,907,320]},
  {"id":"118","name":"《瘟疫》","leibie":5,"pinzhi":4,"kinds":[501],"changdu":[0,0],"dyAt":[1,2],"eps":null,"qiangdu":1,"suoshu":[3],"limit":1016,"prob":70,"chushou":[1,907,480]},
  {"id":"119","name":"《回响》","leibie":5,"pinzhi":6,"kinds":[501],"changdu":[0,0],"dyAt":[1,2],"eps":null,"qiangdu":1,"suoshu":[3],"limit":1016,"prob":30,"chushou":[1,907,960]},
  {"id":"120","name":"《雨夜》","leibie":5,"pinzhi":6,"kinds":[501],"changdu":[0,0],"dyAt":[1,2],"eps":null,"qiangdu":1,"suoshu":[4],"limit":1016,"prob":10,"chushou":[1,907,1000]},
  {"id":"121","name":"《田园不归》","leibie":5,"pinzhi":6,"kinds":[501],"changdu":[0,0],"dyAt":[1,2],"eps":null,"qiangdu":1,"suoshu":[4],"limit":1016,"prob":10,"chushou":[1,907,3600]},
  {"id":"122","name":"失传密卷","leibie":5,"pinzhi":6,"kinds":[501],"changdu":[0,0],"dyAt":[1,2],"eps":null,"qiangdu":1,"suoshu":[5,6,7,8,9],"limit":1016,"prob":5,"chushou":[1,907,6000]},
  {"id":"123","name":"《激斗》","leibie":5,"pinzhi":6,"kinds":[501],"changdu":[0,0],"dyAt":[1,2],"eps":null,"qiangdu":1,"suoshu":[6],"limit":1016,"prob":100,"chushou":[1,907,4000]},
  {"id":"124","name":"《为国为民》","leibie":5,"pinzhi":6,"kinds":[501],"changdu":[0,0],"dyAt":[1,2],"eps":null,"qiangdu":1,"suoshu":[6],"limit":1016,"prob":100,"chushou":[1,907,4000]},
  {"id":"125","name":"《临渊不惧》","leibie":5,"pinzhi":6,"kinds":[501],"changdu":[0,0],"dyAt":[1,2],"eps":null,"qiangdu":1,"suoshu":[7],"limit":1016,"prob":100,"chushou":[1,907,5000]},
  {"id":"126","name":"《江湖儿女》","leibie":5,"pinzhi":6,"kinds":[501],"changdu":[0,0],"dyAt":[1,2],"eps":null,"qiangdu":1,"suoshu":[7],"limit":1016,"prob":100,"chushou":[1,907,5000]},
  {"id":"127","name":"《梦魇》","leibie":5,"pinzhi":4,"kinds":[501],"changdu":[0,0],"dyAt":[1,2],"eps":null,"qiangdu":1,"suoshu":[8],"limit":1016,"prob":100,"chushou":[1,907,7000]},
  {"id":"128","name":"《以身饲虎》","leibie":5,"pinzhi":4,"kinds":[501],"changdu":[0,0],"dyAt":[1,2],"eps":null,"qiangdu":1,"suoshu":[8],"limit":1016,"prob":100,"chushou":[1,907,7000]},
  {"id":"129","name":"《远征》","leibie":5,"pinzhi":4,"kinds":[501],"changdu":[0,0],"dyAt":[1,2],"eps":null,"qiangdu":1,"suoshu":[9],"limit":1016,"prob":100,"chushou":[1,907,7000]},
  {"id":"130","name":"《浪迹天涯》","leibie":5,"pinzhi":4,"kinds":[501],"changdu":[0,0],"dyAt":[1,2],"eps":null,"qiangdu":1,"suoshu":[9],"limit":1016,"prob":100,"chushou":[1,907,7000]},
  {"id":"131","name":"软剑","leibie":5,"pinzhi":6,"kinds":[501],"changdu":[0,0],"dyAt":[1,2],"eps":null,"qiangdu":1,"suoshu":[8,9],"limit":0,"prob":100,"chushou":[1,907,6000]},
  {"id":"132","name":"重剑","leibie":5,"pinzhi":6,"kinds":[501],"changdu":[0,0],"dyAt":[1,2],"eps":null,"qiangdu":1,"suoshu":[8,9],"limit":0,"prob":100,"chushou":[1,907,6000]},
  {"id":"150","name":"隐形鱼","leibie":1,"pinzhi":6,"kinds":[101,540],"changdu":[8,32],"dyAt":[3,7],"eps":{"atk":3500,"def":1380},"qiangdu":1,"suoshu":[4],"limit":0,"prob":10,"chushou":[1,907,1888]},
  {"id":"151","name":"灵魂鱼","leibie":1,"pinzhi":6,"kinds":[101,540],"changdu":[9,36],"dyAt":[3,7],"eps":{"speed":600,"hp_max":18500},"qiangdu":1,"suoshu":[5],"limit":0,"prob":10,"chushou":[1,907,1888]},
  {"id":"152","name":"血鹦鹉","leibie":1,"pinzhi":6,"kinds":[101,164,540],"changdu":[4.2,16.8],"dyAt":[3,7],"eps":{"def":1138,"hp_max":16750},"qiangdu":118,"suoshu":[6,7,8,9],"limit":1013,"prob":1000,"chushou":[1,907,142]},
  {"id":"153","name":"玩具鲨","leibie":1,"pinzhi":6,"kinds":[101,540],"changdu":[15,60],"dyAt":[3,7],"eps":{"atk":3500,"fanbao":450},"qiangdu":1,"suoshu":[6],"limit":0,"prob":100,"chushou":[1,907,1888]},
  {"id":"154","name":"兰寿金鱼","leibie":1,"pinzhi":4,"kinds":[101,159],"changdu":[5.6,22.4],"dyAt":[2,4],"eps":{"atk":2352,"def":1026},"qiangdu":97,"suoshu":[6,7,8,9],"limit":0,"prob":4000,"chushou":[1,907,27]},
  {"id":"155","name":"天竺鲷","leibie":1,"pinzhi":3,"kinds":[101,163],"changdu":[5.9,23.6],"dyAt":[1,2],"eps":{"atk":2680,"hp_max":13400},"qiangdu":94,"suoshu":[6],"limit":0,"prob":3000,"chushou":[1,907,92]},
  {"id":"156","name":"剑尾鱼","leibie":1,"pinzhi":3,"kinds":[101,158],"changdu":[3.3,13.2],"dyAt":[1,2],"eps":{"atk":2680,"def":1012},"qiangdu":94,"suoshu":[6],"limit":0,"prob":3000,"chushou":[1,907,92]},
  {"id":"157","name":"弹涂鱼","leibie":1,"pinzhi":3,"kinds":[101,156],"changdu":[10.2,40.8],"dyAt":[1,2],"eps":{"speed":888},"qiangdu":94,"suoshu":[6],"limit":0,"prob":3000,"chushou":[1,907,92]},
  {"id":"158","name":"龙睛金鱼","leibie":1,"pinzhi":3,"kinds":[101,160],"changdu":[4.8,19.2],"dyAt":[1,2],"eps":{"atk":2710,"hp_max":11200},"qiangdu":86,"suoshu":[6,7,8,9],"limit":0,"prob":3000,"chushou":[1,907,20]},
  {"id":"159","name":"彩虹鱼","leibie":1,"pinzhi":3,"kinds":[101,155],"changdu":[3.7,14.8],"dyAt":[1,2],"eps":{"speed":432,"def":1012},"qiangdu":94,"suoshu":[6],"limit":0,"prob":3000,"chushou":[1,907,92]},
  {"id":"160","name":"桶眼鱼","leibie":2,"pinzhi":4,"kinds":[201,292],"changdu":[27.5,110],"dyAt":[2,4],"eps":{"hsfanji":400,"hsxixue":770},"qiangdu":106,"suoshu":[6],"limit":0,"prob":2000,"chushou":[1,907,114]},
  {"id":"161","name":"鳄雀鳝","leibie":2,"pinzhi":4,"kinds":[201,285],"changdu":[74.1,296.4],"dyAt":[2,4],"eps":{"hslianji":770,"hsbaoji":400},"qiangdu":106,"suoshu":[6],"limit":0,"prob":2000,"chushou":[1,907,114]},
  {"id":"162","name":"鳗鲡","leibie":2,"pinzhi":3,"kinds":[201,290],"changdu":[37.2,148.8],"dyAt":[1,2],"eps":{"hsshanbi":500,"hsjiyun":500},"qiangdu":94,"suoshu":[6],"limit":0,"prob":3000,"chushou":[1,907,92]},
  {"id":"163","name":"噬人鲨","leibie":3,"pinzhi":6,"kinds":[301,540],"changdu":[167.4,669.6],"dyAt":[3,7],"eps":{"atk_per":1160,"atk":3580},"qiangdu":118,"suoshu":[6],"limit":1013,"prob":50,"chushou":[1,907,300]},
  {"id":"164","name":"锯鲨","leibie":3,"pinzhi":6,"kinds":[301,333,540],"changdu":[107.4,429.6],"dyAt":[3,7],"eps":{"atk_per":750,"def_per":550},"qiangdu":118,"suoshu":[6],"limit":0,"prob":100,"chushou":[1,907,142]},
  {"id":"165","name":"古龙鱼","leibie":3,"pinzhi":6,"kinds":[301,540],"changdu":[120,480],"dyAt":[3,7],"eps":{"speed_per":600,"atk_per":600},"qiangdu":1,"suoshu":[6],"limit":0,"prob":100,"chushou":[1,907,1888]},
  {"id":"166","name":"线翎电鳗","leibie":3,"pinzhi":4,"kinds":[301,339],"changdu":[91.6,366.4],"dyAt":[2,4],"eps":{"atk_per":970,"speed":486},"qiangdu":106,"suoshu":[6],"limit":0,"prob":100,"chushou":[1,907,114]},
  {"id":"167","name":"弓背鱼","leibie":3,"pinzhi":4,"kinds":[301,332],"changdu":[99.4,397.6],"dyAt":[2,4],"eps":{"hp_max_per":970,"def":1138},"qiangdu":106,"suoshu":[6],"limit":0,"prob":800,"chushou":[1,907,114]},
  {"id":"168","name":"裸臀鱼","leibie":3,"pinzhi":4,"kinds":[301,336],"changdu":[115,460],"dyAt":[2,4],"eps":{"def_per":970,"hp_max":15075},"qiangdu":106,"suoshu":[6],"limit":0,"prob":600,"chushou":[1,907,114]},
  {"id":"169","name":"大青鲨","leibie":3,"pinzhi":3,"kinds":[301,331],"changdu":[184.8,739.2],"dyAt":[1,2],"eps":{"atk_per":900,"def":1050},"qiangdu":86,"suoshu":[6,7,8,9],"limit":0,"prob":400,"chushou":[1,907,20]},
  {"id":"170","name":"珍珠魟","leibie":3,"pinzhi":3,"kinds":[301,340],"changdu":[167,668],"dyAt":[1,2],"eps":{"def_per":910,"atk":2500},"qiangdu":86,"suoshu":[6,7,8,9],"limit":0,"prob":2000,"chushou":[1,907,20]},
  {"id":"171","name":"龙鱼","leibie":3,"pinzhi":2,"kinds":[301,335],"changdu":[105,420],"dyAt":[1,2],"eps":{"hp_max_per":310,"def_per":600},"qiangdu":82,"suoshu":[6],"limit":0,"prob":4000,"chushou":[1,907,70]},
  {"id":"172","name":"鼠鲨","leibie":3,"pinzhi":2,"kinds":[301,337],"changdu":[92.5,370],"dyAt":[1,2],"eps":{"speed":632,"atk_per":600},"qiangdu":75,"suoshu":[6,7,8,9],"limit":0,"prob":4000,"chushou":[1,907,13]},
  {"id":"173","name":"赤魟","leibie":3,"pinzhi":2,"kinds":[301,330],"changdu":[109,436],"dyAt":[1,2],"eps":{"atk_per":800,"def":1100},"qiangdu":75,"suoshu":[6,7,8,9],"limit":0,"prob":500,"chushou":[1,907,13]},
  {"id":"174","name":"章鱼(吸)","leibie":4,"pinzhi":6,"kinds":[401,540],"changdu":[100,400],"dyAt":[3,7],"eps":{"hp_max":8000,"xixue":1000},"qiangdu":1,"suoshu":[6,7],"limit":0,"prob":100,"chushou":[1,907,1888]},
  {"id":"175","name":"章鱼(反)","leibie":4,"pinzhi":6,"kinds":[401,540],"changdu":[100,400],"dyAt":[3,7],"eps":{"hp_max":8000,"fanji":1000},"qiangdu":1,"suoshu":[6,7],"limit":0,"prob":100,"chushou":[1,907,1888]},
  {"id":"176","name":"章鱼(连)","leibie":4,"pinzhi":6,"kinds":[401,540],"changdu":[100,400],"dyAt":[3,7],"eps":{"hp_max":8000,"lianji":1000},"qiangdu":1,"suoshu":[6,7],"limit":0,"prob":100,"chushou":[1,907,1888]},
  {"id":"177","name":"章鱼(闪)","leibie":4,"pinzhi":6,"kinds":[401,540],"changdu":[100,400],"dyAt":[3,7],"eps":{"hp_max":8000,"shanbi":1000},"qiangdu":1,"suoshu":[6,7],"limit":0,"prob":100,"chushou":[1,907,1888]},
  {"id":"178","name":"章鱼(晕)","leibie":4,"pinzhi":6,"kinds":[401,540],"changdu":[100,400],"dyAt":[3,7],"eps":{"hp_max":8000,"jiyun":1000},"qiangdu":1,"suoshu":[6,7],"limit":0,"prob":100,"chushou":[1,907,1888]},
  {"id":"179","name":"章鱼(暴)","leibie":4,"pinzhi":6,"kinds":[401,540],"changdu":[100,400],"dyAt":[3,7],"eps":{"hp_max":8000,"baoji":1000},"qiangdu":1,"suoshu":[6,7],"limit":0,"prob":100,"chushou":[1,907,1888]},
  {"id":"180","name":"小飞象章鱼","leibie":4,"pinzhi":4,"kinds":[401,455],"changdu":[23.5,94],"dyAt":[2,4],"eps":{"xixue":370,"lianji":800},"qiangdu":106,"suoshu":[6],"limit":0,"prob":1200,"chushou":[1,907,114]},
  {"id":"181","name":"裸海蝶","leibie":4,"pinzhi":3,"kinds":[401,453],"changdu":[1.5,6],"dyAt":[1,2],"eps":{"shanbi":700,"lianji":340},"qiangdu":94,"suoshu":[6],"limit":0,"prob":1500,"chushou":[1,907,92]},
  {"id":"182","name":"鲍鱼","leibie":4,"pinzhi":2,"kinds":[401,447],"changdu":[6.5,26],"dyAt":[1,2],"eps":{"shanbi":590,"def":610},"qiangdu":75,"suoshu":[6,7,8,9],"limit":0,"prob":5000,"chushou":[1,907,13]},
  {"id":"183","name":"海蛇","leibie":4,"pinzhi":2,"kinds":[401,451],"changdu":[26,104],"dyAt":[1,2],"eps":{"baoji":590,"def":610},"qiangdu":75,"suoshu":[6,7,8,9],"limit":0,"prob":5000,"chushou":[1,907,13]},
  {"id":"184","name":"象拔蚌","leibie":4,"pinzhi":2,"kinds":[401,457],"changdu":[8.8,35.2],"dyAt":[1,2],"eps":{"fanji":310,"jiyun":600},"qiangdu":82,"suoshu":[6],"limit":0,"prob":2000,"chushou":[1,907,92]},
  {"id":"185","name":"蝌蚪","leibie":4,"pinzhi":1,"kinds":[401,452],"changdu":[1,4],"dyAt":[1,2],"eps":{"hp_max":11000},"qiangdu":58,"suoshu":[6,7,8,9],"limit":0,"prob":5000,"chushou":[1,907,6]},
  {"id":"186","name":"鳄冰鱼","leibie":1,"pinzhi":3,"kinds":[101,157],"changdu":[6.8,27.2],"dyAt":[1,2],"eps":{"atk":2864,"speed":480},"qiangdu":105,"suoshu":[7],"limit":0,"prob":3000,"chushou":[1,907,100]},
  {"id":"187","name":"鳀鱼","leibie":1,"pinzhi":2,"kinds":[101,162],"changdu":[4.8,19.2],"dyAt":[1,2],"eps":{"atk":2800,"hp_max":9750},"qiangdu":82,"suoshu":[7],"limit":0,"prob":4000,"chushou":[1,907,70]},
  {"id":"188","name":"铅笔鱼","leibie":1,"pinzhi":2,"kinds":[101,161],"changdu":[2.6,10.4],"dyAt":[1,2],"eps":{"hp_max":9130,"speed":420},"qiangdu":75,"suoshu":[6,7,8,9],"limit":0,"prob":5000,"chushou":[1,907,13]},
  {"id":"189","name":"冰川鱼","leibie":1,"pinzhi":2,"kinds":[101,154],"changdu":[14.7,58.8],"dyAt":[1,2],"eps":{"hp_max":12950,"atk":2506},"qiangdu":91,"suoshu":[7],"limit":0,"prob":4000,"chushou":[1,907,80]},
  {"id":"190","name":"吞噬鳗","leibie":2,"pinzhi":6,"kinds":[201,293,540],"changdu":[52.9,211.6],"dyAt":[3,7],"eps":{"hsshanbi":500,"hsxixue":860},"qiangdu":132,"suoshu":[7],"limit":0,"prob":300,"chushou":[1,907,145]},
  {"id":"191","name":"蟹虎鱼","leibie":2,"pinzhi":6,"kinds":[201,294,540],"changdu":[49.2,196.8],"dyAt":[3,7],"eps":{"hsfanji":700,"hslianji":700},"qiangdu":132,"suoshu":[7],"limit":0,"prob":1000,"chushou":[1,907,145]},
  {"id":"192","name":"钻石鱼","leibie":2,"pinzhi":6,"kinds":[201,540],"changdu":[60,240],"dyAt":[3,7],"eps":{"baonue":2000},"qiangdu":1,"suoshu":[7],"limit":0,"prob":300,"chushou":[1,907,1888]},
  {"id":"193","name":"枯叶鱼","leibie":2,"pinzhi":4,"kinds":[201,287],"changdu":[13,52],"dyAt":[2,4],"eps":{"hslianji":750,"hsshanbi":380},"qiangdu":97,"suoshu":[6,7,8,9],"limit":0,"prob":2000,"chushou":[1,907,27]},
  {"id":"194","name":"长颌鱼","leibie":2,"pinzhi":4,"kinds":[201,295],"changdu":[34.4,137.6],"dyAt":[2,4],"eps":{"hsfanji":750,"hsshanbi":380},"qiangdu":97,"suoshu":[6,7,8,9],"limit":0,"prob":2000,"chushou":[1,907,27]},
  {"id":"195","name":"东星斑","leibie":2,"pinzhi":4,"kinds":[201,284],"changdu":[44.3,177.2],"dyAt":[2,4],"eps":{"hsshanbi":500,"hsfanji":720},"qiangdu":118,"suoshu":[7],"limit":0,"prob":2000,"chushou":[1,907,122]},
  {"id":"196","name":"雷龙鱼","leibie":2,"pinzhi":3,"kinds":[201,289],"changdu":[19.7,78.8],"dyAt":[1,2],"eps":{"hsjiyun":480,"hsxixue":520},"qiangdu":86,"suoshu":[6,7,8,9],"limit":0,"prob":2000,"chushou":[1,907,20]},
  {"id":"197","name":"蓝鳍鱼","leibie":2,"pinzhi":3,"kinds":[201,288],"changdu":[78.9,315.6],"dyAt":[1,2],"eps":{"hsjiyun":630,"hsbaoji":460},"qiangdu":105,"suoshu":[7],"limit":0,"prob":3000,"chushou":[1,907,100]},
  {"id":"198","name":"犬牙鱼","leibie":2,"pinzhi":3,"kinds":[201,291],"changdu":[63.4,253.6],"dyAt":[1,2],"eps":{"hsxixue":730,"hslianji":360},"qiangdu":105,"suoshu":[7],"limit":0,"prob":3000,"chushou":[1,907,100]},
  {"id":"199","name":"帆蜥鱼","leibie":2,"pinzhi":2,"kinds":[201,286],"changdu":[28.6,114.4],"dyAt":[1,2],"eps":{"hsbaoji":440,"hsshanbi":440},"qiangdu":75,"suoshu":[6,7,8,9],"limit":0,"prob":3000,"chushou":[1,907,13]},
  {"id":"200","name":"独角鲸","leibie":3,"pinzhi":6,"kinds":[301,540],"changdu":[265.7,1062.8],"dyAt":[3,7],"eps":{"def_per":1260,"def":1380},"qiangdu":132,"suoshu":[7],"limit":1011,"prob":50,"chushou":[1,907,332]},
  {"id":"201","name":"狼鳗","leibie":3,"pinzhi":3,"kinds":[301,334],"changdu":[123.5,494],"dyAt":[1,2],"eps":{"hp_max_per":1100,"speed":480},"qiangdu":105,"suoshu":[7],"limit":0,"prob":200,"chushou":[1,907,105]},
  {"id":"202","name":"梭鱼","leibie":3,"pinzhi":1,"kinds":[301,338],"changdu":[104.5,418],"dyAt":[1,2],"eps":{"atk":2356,"hp_max_per":300},"qiangdu":64,"suoshu":[6,7,8,9],"limit":0,"prob":5000,"chushou":[1,907,6]},
  {"id":"203","name":"海豹","leibie":4,"pinzhi":6,"kinds":[401,540],"changdu":[58.6,234.4],"dyAt":[3,7],"eps":{"baoji":960,"lianbao":460},"qiangdu":132,"suoshu":[7],"limit":1008,"prob":100,"chushou":[1,907,302]},
  {"id":"204","name":"吸血鬼乌贼","leibie":4,"pinzhi":4,"kinds":[401,454],"changdu":[12.6,50.4],"dyAt":[2,4],"eps":{"xixue":1220,"atk":1587},"qiangdu":118,"suoshu":[7],"limit":0,"prob":2000,"chushou":[1,907,122]},
  {"id":"205","name":"萤火鱿鱼","leibie":4,"pinzhi":4,"kinds":[401,456],"changdu":[7.6,30.4],"dyAt":[2,4],"eps":{"shanbi":1220,"speed":500},"qiangdu":118,"suoshu":[7],"limit":0,"prob":2000,"chushou":[1,907,122]},
  {"id":"206","name":"多足鲎","leibie":4,"pinzhi":3,"kinds":[401,448],"changdu":[41,164],"dyAt":[1,2],"eps":{"xixue":590,"def":610},"qiangdu":86,"suoshu":[6,7,8,9],"limit":0,"prob":3000,"chushou":[1,907,20]},
  {"id":"207","name":"海蛞蝓","leibie":4,"pinzhi":3,"kinds":[401,450],"changdu":[3.2,12.8],"dyAt":[1,2],"eps":{"jiyun":590,"def":610},"qiangdu":75,"suoshu":[6,7,8,9],"limit":0,"prob":5000,"chushou":[1,907,13]},
  {"id":"208","name":"海葵","leibie":4,"pinzhi":2,"kinds":[401,449],"changdu":[14,56],"dyAt":[1,2],"eps":{"lianji":590,"def":610},"qiangdu":75,"suoshu":[6,7,8,9],"limit":0,"prob":5000,"chushou":[1,907,13]},
  {"id":"209","name":"大珍珠蚌","leibie":4,"pinzhi":4,"kinds":[401],"changdu":[38,152],"dyAt":[2,4],"eps":{"def":800},"qiangdu":139,"suoshu":[8,9],"limit":0,"prob":600,"chushou":[1,909,10]},
  {"id":"210","name":"棘冠海星","leibie":4,"pinzhi":4,"kinds":[401,458],"changdu":[23,92],"dyAt":[2,4],"eps":{"jiyun":1020,"lianji":430},"qiangdu":139,"suoshu":[8],"limit":0,"prob":2000,"chushou":[1,907,160]},
  {"id":"211","name":"红羽海星","leibie":4,"pinzhi":4,"kinds":[401,459],"changdu":[8,32],"dyAt":[2,4],"eps":{"xixue":1020,"lianji":430},"qiangdu":139,"suoshu":[8],"limit":0,"prob":2000,"chushou":[1,907,160]},
  {"id":"212","name":"虎鲸","leibie":4,"pinzhi":6,"kinds":[401],"changdu":[250,1000],"dyAt":[3,7],"eps":{"fanji":1320,"def":704},"qiangdu":155,"suoshu":[8],"limit":1015,"prob":80,"chushou":[1,907,332]},
  {"id":"213","name":"儒艮","leibie":4,"pinzhi":6,"kinds":[401,460],"changdu":[160,640],"dyAt":[3,7],"eps":{"jiyun":1320,"atk":1696},"qiangdu":155,"suoshu":[8],"limit":0,"prob":1000,"chushou":[1,907,190]},
  {"id":"214","name":"镜鱼","leibie":1,"pinzhi":1,"kinds":[101,461],"changdu":[3.8,15.2],"dyAt":[1,2],"eps":{"def":1113},"qiangdu":90,"suoshu":[8],"limit":0,"prob":5000,"chushou":[1,907,67]},
  {"id":"215","name":"反游鲶","leibie":1,"pinzhi":2,"kinds":[101,462],"changdu":[10.5,42],"dyAt":[1,2],"eps":{"hp_max":13021,"speed":507},"qiangdu":106,"suoshu":[8],"limit":0,"prob":4000,"chushou":[1,907,98]},
  {"id":"216","name":"虎皮鱼","leibie":1,"pinzhi":3,"kinds":[101,463],"changdu":[4.3,17.2],"dyAt":[1,2],"eps":{"hp_max":17312},"qiangdu":123,"suoshu":[8],"limit":0,"prob":3000,"chushou":[1,907,129]},
  {"id":"217","name":"盒子鱼","leibie":1,"pinzhi":4,"kinds":[101,464],"changdu":[5.9,23.6],"dyAt":[2,4],"eps":{"def":1305,"speed":520},"qiangdu":139,"suoshu":[8],"limit":0,"prob":2000,"chushou":[1,907,160]},
  {"id":"218","name":"鬼丽鱼","leibie":1,"pinzhi":4,"kinds":[101,465],"changdu":[5.5,22],"dyAt":[2,4],"eps":{"atk":2990,"speed":520},"qiangdu":139,"suoshu":[8],"limit":0,"prob":2000,"chushou":[1,907,160]},
  {"id":"219","name":"接吻鱼","leibie":1,"pinzhi":6,"kinds":[101,466],"changdu":[12,48],"dyAt":[3,7],"eps":{"atk":3320,"def":1410},"qiangdu":155,"suoshu":[8],"limit":0,"prob":1000,"chushou":[1,907,190]},
  {"id":"220","name":"鹦嘴鱼","leibie":2,"pinzhi":3,"kinds":[201,467],"changdu":[16.9,67.6],"dyAt":[1,2],"eps":{"hsbaoji":800,"hsjiyun":340},"qiangdu":123,"suoshu":[8],"limit":0,"prob":3000,"chushou":[1,907,129]},
  {"id":"221","name":"麒麟鱼","leibie":2,"pinzhi":4,"kinds":[201,468],"changdu":[17.6,70.4],"dyAt":[2,4],"eps":{"hsjiyun":900,"hslianji":380},"qiangdu":139,"suoshu":[8],"limit":0,"prob":100,"chushou":[1,907,160]},
  {"id":"222","name":"地图鱼","leibie":2,"pinzhi":4,"kinds":[201,469],"changdu":[18.2,72.8],"dyAt":[2,4],"eps":{"hsxixue":900,"hsbaoji":380},"qiangdu":139,"suoshu":[8],"limit":0,"prob":100,"chushou":[1,907,160]},
  {"id":"223","name":"三色锦鲤","leibie":2,"pinzhi":6,"kinds":[201],"changdu":[22.1,88.4],"dyAt":[3,7],"eps":{"hsshanbi":650,"hsfanji":500,"hsxixue":400},"qiangdu":155,"suoshu":[8],"limit":1002,"prob":80,"chushou":[1,907,190]},
  {"id":"224","name":"白鲟","leibie":3,"pinzhi":4,"kinds":[301,470],"changdu":[91.6,366.4],"dyAt":[2,4],"eps":{"hp_max_per":1200,"speed":520},"qiangdu":139,"suoshu":[8],"limit":0,"prob":2000,"chushou":[1,907,160]},
  {"id":"225","name":"牛鲨","leibie":3,"pinzhi":6,"kinds":[301,471],"changdu":[99.3,397.2],"dyAt":[3,7],"eps":{"hp_max_per":400,"def_per":1200},"qiangdu":155,"suoshu":[8],"limit":0,"prob":1000,"chushou":[1,907,190]},
  {"id":"235","name":"纯净妖精鱼","leibie":1,"pinzhi":6,"kinds":[101],"changdu":[8,32],"dyAt":[3,7],"eps":{"atk":3800,"lianbao":550},"qiangdu":1,"suoshu":[8],"limit":0,"prob":1000,"chushou":[1,907,2000]},
  {"id":"236","name":"混沌妖精鱼","leibie":1,"pinzhi":6,"kinds":[101],"changdu":[8,32],"dyAt":[3,7],"eps":{"atk":3800,"fanbao":360},"qiangdu":1,"suoshu":[8],"limit":0,"prob":1000,"chushou":[1,907,2000]},
  {"id":"237","name":"水蛭","leibie":4,"pinzhi":1,"kinds":[401,472],"changdu":[2.9,11.6],"dyAt":[1,2],"eps":{"xixue":620,"shanbi":350},"qiangdu":111,"suoshu":[9],"limit":0,"prob":4000,"chushou":[1,907,72]},
  {"id":"238","name":"大鲵","leibie":4,"pinzhi":3,"kinds":[401,473],"changdu":[55,220],"dyAt":[1,2],"eps":{"jiyun":1060,"fanji":260},"qiangdu":144,"suoshu":[9],"limit":0,"prob":1500,"chushou":[1,907,138]},
  {"id":"239","name":"红眼蟾蜍","leibie":4,"pinzhi":4,"kinds":[401,474],"changdu":[7.5,30],"dyAt":[2,4],"eps":{"baoji":1280,"speed":600},"qiangdu":161,"suoshu":[9],"limit":0,"prob":1500,"chushou":[1,907,171]},
  {"id":"240","name":"水獭","leibie":4,"pinzhi":6,"kinds":[401],"changdu":[23,92],"dyAt":[3,7],"eps":{"lianji":1380,"atk":1871},"qiangdu":178,"suoshu":[9],"limit":1014,"prob":90,"chushou":[1,907,364]},
  {"id":"241","name":"花鳅","leibie":1,"pinzhi":2,"kinds":[101,475],"changdu":[2.1,8.4],"dyAt":[1,2],"eps":{"def":1127,"speed":554},"qiangdu":127,"suoshu":[9],"limit":0,"prob":4000,"chushou":[1,907,105]},
  {"id":"242","name":"射水鱼","leibie":1,"pinzhi":3,"kinds":[101,476],"changdu":[4.9,19.6],"dyAt":[1,2],"eps":{"atk":3878},"qiangdu":144,"suoshu":[9],"limit":0,"prob":3000,"chushou":[1,907,138]},
  {"id":"243","name":"盲鱼","leibie":1,"pinzhi":4,"kinds":[101,477],"changdu":[2.8,11.2],"dyAt":[2,4],"eps":{"hp_max":14100,"atk":3119},"qiangdu":161,"suoshu":[9],"limit":0,"prob":1000,"chushou":[1,907,171]},
  {"id":"244","name":"鳜鱼","leibie":2,"pinzhi":2,"kinds":[201,478],"changdu":[22.4,89.6],"dyAt":[1,2],"eps":{"hslianji":830,"hsjiyun":320},"qiangdu":127,"suoshu":[9],"limit":0,"prob":100,"chushou":[1,907,105]},
  {"id":"245","name":"七腮鳗","leibie":2,"pinzhi":3,"kinds":[201,479],"changdu":[19.8,79.2],"dyAt":[1,2],"eps":{"hsbaoji":900,"hsfanji":430},"qiangdu":144,"suoshu":[9],"limit":0,"prob":2000,"chushou":[1,907,138]},
  {"id":"246","name":"恐龙鱼","leibie":2,"pinzhi":3,"kinds":[201,480],"changdu":[23.9,95.6],"dyAt":[1,2],"eps":{"hsxixue":900,"hslianji":430},"qiangdu":144,"suoshu":[9],"limit":0,"prob":2000,"chushou":[1,907,138]},
  {"id":"247","name":"犁头鳐","leibie":2,"pinzhi":4,"kinds":[201,481],"changdu":[28.9,115.6],"dyAt":[2,4],"eps":{"hsshanbi":1070,"hsfanji":400},"qiangdu":161,"suoshu":[9],"limit":0,"prob":1500,"chushou":[1,907,171]},
  {"id":"248","name":"帝王三间鱼","leibie":2,"pinzhi":6,"kinds":[201],"changdu":[33.3,133.2],"dyAt":[3,7],"eps":{"hsjiyun":680,"hsbaoji":580,"hslianji":580},"qiangdu":178,"suoshu":[9],"limit":1012,"prob":100,"chushou":[1,907,388]},
  {"id":"249","name":"鸭嘴鱼","leibie":3,"pinzhi":4,"kinds":[301,482],"changdu":[90.5,362],"dyAt":[2,4],"eps":{"hp_max_per":1300,"speed":560},"qiangdu":161,"suoshu":[9],"limit":0,"prob":1500,"chushou":[1,907,171]},
  {"id":"250","name":"六须鲶鱼","leibie":3,"pinzhi":6,"kinds":[301,483],"changdu":[103.5,414],"dyAt":[3,7],"eps":{"hp_max_per":1400,"hp_max":18223},"qiangdu":178,"suoshu":[9],"limit":0,"prob":1000,"chushou":[1,907,204]},
  {"id":"251","name":"毒沼鱼","leibie":1,"pinzhi":6,"kinds":[101],"changdu":[4,16],"dyAt":[3,7],"eps":{"speed":650,"baonue":360},"qiangdu":1,"suoshu":[9],"limit":0,"prob":1500,"chushou":[1,907,2000]}
]