[1,["ecpdLyjvZBwrvm+cedCcQy","b87lZ1+fVKJKS9iaaqAmYJ","6esT15+UpL3IuM2C1faXY2","48MITLTtRJN6TBsS73gFsZ","b8A3SB739CJZwCgedcrNv7"],["node","root","_parent","_spriteFrame","_textureSetter","data","_defaultClip"],[["cc.Node",["_name","_prefab","_children","_parent","_components","_contentSize","_color","_trs"],2,4,2,1,9,5,5,7],["cc.PrefabInfo",["fileId","root","asset"],2,1,1],["cc.Animation",["playOnLoad","node","_clips","_defaultClip"],2,1,3,6],"cc.SpriteFrame",["cc.Prefab",["_name"],2],["cc.Sprite",["_sizeMode","_isTrimmedMode","node","_materials","_spriteFrame"],1,1,3,6]],[[1,0,1,2],[0,0,2,1,2],[0,0,3,2,1,2],[1,0,1,2,2],[5,0,1,2,3,4,3],[4,0,2],[0,0,3,4,1,5,2],[0,0,4,1,6,5,7,2],[1,1,2,1],[2,1,1],[2,0,1,2,3,2]],[[[{"name":"驱魔令","rect":[12,13,71,72],"offset":[2.5,-4],"originalSize":[90,90],"capInsets":[0,0,0,0]}],[3],0,[0],[4],[2]],[[[5,"百恋_公共_驱魔令"],[1,"root",[-2],[8,-1,0]],[1,"百恋_战斗场景特效_公用道具特效_红",[-4],[0,"f6ZXJ8o0NGF5N38rk4xOsH",-3]],[2,"position",1,[-5,2],[3,"1768HiGARNaoyAvM2o3PlD",1,0]],[6,"sprite",3,[[4,0,false,-6,[0],1],[9,-7]],[3,"24MVL74RhOqINJoHjo0+ow",1,0],[5,70,70]],[7,"sprite",[[4,0,false,-8,[2],3],[10,true,-9,[5],4]],[0,"24MVL74RhOqINJoHjo0+ow",2],[4,4279242987],[5,201,202],[0,0,0,0,0,0,1,0.5,0.5,1]],[2,"position",2,[5],[0,"1768HiGARNaoyAvM2o3PlD",2]]],0,[0,1,1,0,-1,3,0,1,2,0,-1,6,0,-1,4,0,0,4,0,0,4,0,0,5,0,0,5,0,5,1,2,2,3,5,2,6,9],[0,0,0,0,0,0],[-1,3,-1,3,6,-1],[0,3,0,4,1,1]]]]